Workbook

Sheet Sep
A1: location | B1: date | C1: reserved_at | D1: appointment_type | E1: status | F1: first_name | G1: last_name | H1: address_line_1 | I1: address_line_2 | J1: address_line_3 | K1: address_line_4 | L1: address_line_5 | M1: Postcode | N1: Email | O1: sex_at_birth | P1: dob | Q1: Age | R1: reference | S1: phone | T1: product_code | U1: extra_product_options | V1: totals | W1: process_status | X1: tags | Y1: FHM_Identifier | Z1: patient_id_number_prefix | AA1: single_use_invitation_code | AB1: postcode_region | AC1: Prefix | AD1: Region | AE1: Corporate Or Self Pay
A2: LIH | B2: 45670 | C2: 45660 | D2: screening | E2: Booked | F2: Valentin | G2: Elsip | H2: 80749 Washington Junction | I2: Room 1862 | M2: IG9 6EL | N2: velsip0@microsoft.com | O2: male | P2: 27157 | Q2: =DATEDIF(P2,B2,"Y") -> 50 | R2: F10FAFDF | S2: 447799822636 | T2: Advanced | V2: {=IFERROR( _xlfn.XLOOKUP(1, (tblPrices[Prefix]=$AC2)*(tblPrices[Product Code]=$T2), tblPrices[Price] ), 0 ) + IF(ISNUMBER(SEARCH("Mammogram",$U2)), IFERROR(_xlfn.XLOOKUP(1,(tblPrices[Prefix]=$AC2)*(tblPrices[Product Code]="Mammogram"),tblPrices[Price]),0), 0 ) + IF(ISNUMBER(SEARCH("PSA",$U2)), IFERROR(_xlfn.XLOOKUP(1,(tblPrices[Prefix]=$AC2)*(tblPrices[Product Code]="PSA"),tblPrices[Price]),0), 0 )} -> 543.38 | W2: dispatched | X2: paid,fasting,online,viewed_online | Z2: 19485502 | AA2: U48 | AB2: {=_xlfn.LET(_xlpm.pc, UPPER(TRIM(M2)), LEFT(_xlpm.pc, MIN(FIND({0,1,2,3,4,5,6,7,8,9}, _xlpm.pc&"0123456789"))-1))} -> IG | AC2: U48 | AD2: =VLOOKUP(AB2, postcode_table!A:B, 2, FALSE) -> Ilford | AE2: =IFERROR(_xlfn.XLOOKUP(AC2, price_lookup_table!$C:$C, price_lookup_table!$B:$B), "") -> Corporate
A3: MNR | B3: 45670 | C3: 45666 | D3: screening | E3: Booked | F3: Carlin | G3: Towson | H3: 2 Rieder Center | I3: Apt 153 | M3: MK44 3HD | N3: ctowson1@aboutads.info | O3: male | P3: 26347 | Q3: =DATEDIF(P3,B3,"Y") -> 52 | R3: 8B53BEB1 | S3: 447831777666 | T3: Advanced | V3: {=IFERROR( _xlfn.XLOOKUP(1, (tblPrices[Prefix]=$AC3)*(tblPrices[Product Code]=$T3), tblPrices[Price] ), 0 ) + IF(ISNUMBER(SEARCH("Mammogram",$U3)), IFERROR(_xlfn.XLOOKUP(1,(tblPrices[Prefix]=$AC3)*(tblPrices[Product Code]="Mammogram"),tblPrices[Price]),0), 0 ) + IF(ISNUMBER(SEARCH("PSA",$U3)), IFERROR(_xlfn.XLOOKUP(1,(tblPrices[Prefix]=$AC3)*(tblPrices[Product Code]="PSA"),tblPrices[Price]),0), 0 )} -> 543.38 | W3: dispatched | X3: paid,fasting,green,online,ecg_uploaded | Z3: 12267863 | AA3: U48 | AB3: {=_xlfn.LET(_xlpm.pc, UPPER(TRIM(M3)), LEFT(_xlpm.pc, MIN(FIND({0,1,2,3,4,5,6,7,8,9}, _xlpm.pc&"0123456789"))-1))} -> MK | AC3: U48 | AD3: =VLOOKUP(AB3, postcode_table!A:B, 2, FALSE) -> Milton Keynes | AE3: =IFERROR(_xlfn.XLOOKUP(AC3, price_lookup_table!$C:$C, price_lookup_table!$B:$B), "") -> Corporate
A4: LIH | B4: 45670 | C4: 45660 | D4: screening | E4: Booked | F4: Woodie | G4: Kynsey | H4: 5418 Debra Court | I4: PO Box 20094 | M4: SE3 8BP | N4: wkynsey2@squidoo.com | O4: male | P4: 29270 | Q4: =DATEDIF(P4,B4,"Y") -> 44 | R4: CD77C3D1 | S4: 447766258553 | T4: Advanced | V4: {=IFERROR( _xlfn.XLOOKUP(1, (tblPrices[Prefix]=$AC4)*(tblPrices[Product Code]=$T4), tblPrices[Price] ), 0 ) + IF(ISNUMBER(SEARCH("Mammogram",$U4)), IFERROR(_xlfn.XLOOKUP(1,(tblPrices[Prefix]=$AC4)*(tblPrices[Product Code]="Mammogram"),tblPrices[Price]),0), 0 ) + IF(ISNUMBER(SEARCH("PSA",$U4)), IFERROR(_xlfn.XLOOKUP(1,(tblPrices[Prefix]=$AC4)*(tblPrices[Product Code]="PSA"),tblPrices[Price]),0), 0 )} -> 543.38 | W4: dispatched | X4: paid,fasting,online,viewed_online | Z4: 22003492 | AA4: U48 | AB4: {=_xlfn.LET(_xlpm.pc, UPPER(TRIM(M4)), LEFT(_xlpm.pc, MIN(FIND({0,1,2,3,4,5,6,7,8,9}, _xlpm.pc&"0123456789"))-1))} -> SE | AC4: U48 | AD4: =VLOOKUP(AB4, postcode_table!A:B, 2, FALSE) -> South East London | AE4: =IFERROR(_xlfn.XLOOKUP(AC4, price_lookup_table!$C:$C, price_lookup_table!$B:$B), "") -> Corporate
A5: GAR | B5: 45671 | C5: 45660 | D5: screening | E5: Booked | F5: Randal | G5: Fisk | H5: 3 Waxwing Pass | I5: Apt 382 | M5: N20 0RH | N5: rfisk3@mashable.com | O5: female | P5: 27760 | Q5: =DATEDIF(P5,B5,"Y") -> 49 | R5: 74C623C0 | S5: 447841131185 | T5: Select | V5: {=IFERROR( _xlfn.XLOOKUP(1, (tblPrices[Prefix]=$AC5)*(tblPrices[Product Code]=$T5), tblPrices[Price] ), 0 ) + IF(ISNUMBER(SEARCH("Mammogram",$U5)), IFERROR(_xlfn.XLOOKUP(1,(tblPrices[Prefix]=$AC5)*(tblPrices[Product Code]="Mammogram"),tblPrices[Price]),0), 0 ) + IF(ISNUMBER(SEARCH("PSA",$U5)), IFERROR(_xlfn.XLOOKUP(1,(tblPrices[Prefix]=$AC5)*(tblPrices[Product Code]="PSA"),tblPrices[Price]),0), 0 )} -> 357.38 | W5: dispatched | X5: paid,fasting,amber,online,viewed_online | Z5: 21689026 | AA5: U48 | AB5: {=_xlfn.LET(_xlpm.pc, UPPER(TRIM(M5)), LEFT(_xlpm.pc, MIN(FIND({0,1,2,3,4,5,6,7,8,9}, _xlpm.pc&"0123456789"))-1))} -> N | AC5: U48 | AD5: =VLOOKUP(AB5, postcode_table!A:B, 2, FALSE) -> North London | AE5: =IFERROR(_xlfn.XLOOKUP(AC5, price_lookup_table!$C:$C, price_lookup_table!$B:$B), "") -> Corporate
A6: GAR | B6: 45672 | C6: 45665 | D6: screening | E6: Booked | F6: Marie-ann | G6: Trathen | H6: 73 Vernon Junction | I6: Room 1463 | M6: NW3 4BY | N6: mtrathen4@howstuffworks.com | O6: female | P6: 25543 | Q6: =DATEDIF(P6,B6,"Y") -> 55 | R6: B5B724D4 | S6: 447943299012 | T6: Advanced | U6: MAMMOGRAM | V6: {=IFERROR( _xlfn.XLOOKUP(1, (tblPrices[Prefix]=$AC6)*(tblPrices[Product Code]=$T6), tblPrices[Price] ), 0 ) + IF(ISNUMBER(SEARCH("Mammogram",$U6)), IFERROR(_xlfn.XLOOKUP(1,(tblPrices[Prefix]=$AC6)*(tblPrices[Product Code]="Mammogram"),tblPrices[Price]),0), 0 ) + IF(ISNUMBER(SEARCH("PSA",$U6)), IFERROR(_xlfn.XLOOKUP(1,(tblPrices[Prefix]=$AC6)*(tblPrices[Product Code]="PSA"),tblPrices[Price]),0), 0 )} -> 690.38 | W6: dispatched | X6: paid,fasting,green,online,viewed_online | Z6: 22008182 | AA6: U48 | AB6: {=_xlfn.LET(_xlpm.pc, UPPER(TRIM(M6)), LEFT(_xlpm.pc, MIN(FIND({0,1,2,3,4,5,6,7,8,9}, _xlpm.pc&"0123456789"))-1))} -> NW | AC6: U48 | AD6: =VLOOKUP(AB6, postcode_table!A:B, 2, FALSE) -> North West London | AE6: =IFERROR(_xlfn.XLOOKUP(AC6, price_lookup_table!$C:$C, price_lookup_table!$B:$B), "") -> Corporate
A7: ALB | B7: 45674 | C7: 45663 | D7: screening | E7: Booked | F7: Siusan | G7: Baskerville | H7: 724 Darwin Junction | I7: PO Box 56845 | M7: AB41 6EE | N7: sbaskerville5@ask.com | O7: male | P7: 32886 | Q7: =DATEDIF(P7,B7,"Y") -> 35 | R7: D202EE3A | S7: 447826541608 | T7: Advanced | V7: {=IFERROR( _xlfn.XLOOKUP(1, (tblPrices[Prefix]=$AC7)*(tblPrices[Product Code]=$T7), tblPrices[Price] ), 0 ) + IF(ISNUMBER(SEARCH("Mammogram",$U7)), IFERROR(_xlfn.XLOOKUP(1,(tblPrices[Prefix]=$AC7)*(tblPrices[Product Code]="Mammogram"),tblPrices[Price]),0), 0 ) + IF(ISNUMBER(SEARCH("PSA",$U7)), IFERROR(_xlfn.XLOOKUP(1,(tblPrices[Prefix]=$AC7)*(tblPrices[Product Code]="PSA"),tblPrices[Price]),0), 0 )} -> 543.38 | W7: dispatched | X7: paid,fasting,online,viewed_online | Z7: 15859179 | AA7: U48 | AB7: {=_xlfn.LET(_xlpm.pc, UPPER(TRIM(M7)), LEFT(_xlpm.pc, MIN(FIND({0,1,2,3,4,5,6,7,8,9}, _xlpm.pc&"0123456789"))-1))} -> AB | AC7: U48 | AD7: =VLOOKUP(AB7, postcode_table!A:B, 2, FALSE) -> Aberdeen | AE7: =IFERROR(_xlfn.XLOOKUP(AC7, price_lookup_table!$C:$C, price_lookup_table!$B:$B), "") -> Corporate
A8: SYC | B8: 45674 | C8: 45663 | D8: screening | E8: Booked | F8: Seth | G8: Witherup | H8: 993 Cherokee Junction | I8: Room 1765 | M8: W8 4SB | N8: switherup6@zimbio.com | O8: male | P8: 28631 | Q8: =DATEDIF(P8,B8,"Y") -> 46 | R8: F5064A01 | S8: 447794842337 | T8: Select | U8: PSA | V8: {=IFERROR( _xlfn.XLOOKUP(1, (tblPrices[Prefix]=$AC8)*(tblPrices[Product Code]=$T8), tblPrices[Price] ), 0 ) + IF(ISNUMBER(SEARCH("Mammogram",$U8)), IFERROR(_xlfn.XLOOKUP(1,(tblPrices[Prefix]=$AC8)*(tblPrices[Product Code]="Mammogram"),tblPrices[Price]),0), 0 ) + IF(ISNUMBER(SEARCH("PSA",$U8)), IFERROR(_xlfn.XLOOKUP(1,(tblPrices[Prefix]=$AC8)*(tblPrices[Product Code]="PSA"),tblPrices[Price]),0), 0 )} -> 469.38 | W8: dispatched | X8: viewed_online,paid,fasting,amber,online | Z8: 22005952 | AA8: U48 | AB8: {=_xlfn.LET(_xlpm.pc, UPPER(TRIM(M8)), LEFT(_xlpm.pc, MIN(FIND({0,1,2,3,4,5,6,7,8,9}, _xlpm.pc&"0123456789"))-1))} -> W | AC8: U48 | AD8: =VLOOKUP(AB8, postcode_table!A:B, 2, FALSE) -> West London | AE8: =IFERROR(_xlfn.XLOOKUP(AC8, price_lookup_table!$C:$C, price_lookup_table!$B:$B), "") -> Corporate
A9: LIN | B9: 45674 | C9: 45664 | D9: screening | E9: Booked | F9: Harry | G9: Yakunchikov | H9: 59 Michigan Hill | I9: Apt 219 | M9: LN10 6PJ | N9: hyakunchikov7@google.es | O9: male | P9: 20340 | Q9: =DATEDIF(P9,B9,"Y") -> 69 | R9: BD65DBE9 | S9: 447709012401 | T9: Advanced | V9: {=IFERROR( _xlfn.XLOOKUP(1, (tblPrices[Prefix]=$AC9)*(tblPrices[Product Code]=$T9), tblPrices[Price] ), 0 ) + IF(ISNUMBER(SEARCH("Mammogram",$U9)), IFERROR(_xlfn.XLOOKUP(1,(tblPrices[Prefix]=$AC9)*(tblPrices[Product Code]="Mammogram"),tblPrices[Price]),0), 0 ) + IF(ISNUMBER(SEARCH("PSA",$U9)), IFERROR(_xlfn.XLOOKUP(1,(tblPrices[Prefix]=$AC9)*(tblPrices[Product Code]="PSA"),tblPrices[Price]),0), 0 )} -> 543.38 | W9: dispatched | X9: paid,fasting,amber,online,viewed_online | Z9: 22007274 | AA9: U48 | AB9: {=_xlfn.LET(_xlpm.pc, UPPER(TRIM(M9)), LEFT(_xlpm.pc, MIN(FIND({0,1,2,3,4,5,6,7,8,9}, _xlpm.pc&"0123456789"))-1))} -> LN | AC9: U48 | AD9: =VLOOKUP(AB9, postcode_table!A:B, 2, FALSE) -> Lincoln | AE9: =IFERROR(_xlfn.XLOOKUP(AC9, price_lookup_table!$C:$C, price_lookup_table!$B:$B), "") -> Corporate
A10: LIH | B10: 45677 | C10: 45660 | D10: screening | E10: Booked | F10: Ferd | G10: Poleye | H10: 0 Melody Road | I10: Room 1024 | M10: KT2 7BS | N10: fpoleye8@techcrunch.com | O10: female | P10: 28703 | Q10: =DATEDIF(P10,B10,"Y") -> 46 | R10: ACF2F7EB | S10: 447740375131 | T10: Advanced | V10: {=IFERROR( _xlfn.XLOOKUP(1, (tblPrices[Prefix]=$AC10)*(tblPrices[Product Code]=$T10), tblPrices[Price] ), 0 ) + IF(ISNUMBER(SEARCH("Mammogram",$U10)), IFERROR(_xlfn.XLOOKUP(1,(tblPrices[Prefix]=$AC10)*(tblPrices[Product Code]="Mammogram"),tblPrices[Price]),0), 0 ) + IF(ISNUMBER(SEARCH("PSA",$U10)), IFERROR(_xlfn.XLOOKUP(1,(tblPrices[Prefix]=$AC10)*(tblPrices[Product Code]="PSA"),tblPrices[Price]),0), 0 )} -> 543.38 | W10: dispatched | X10: viewed_online,paid,fasting,online | Z10: 22003219 | AA10: U48 | AB10: {=_xlfn.LET(_xlpm.pc, UPPER(TRIM(M10)), LEFT(_xlpm.pc, MIN(FIND({0,1,2,3,4,5,6,7,8,9}, _xlpm.pc&"0123456789"))-1))} -> KT | AC10: U48 | AD10: =VLOOKUP(AB10, postcode_table!A:B, 2, FALSE) -> Kingston upon Thames | AE10: =IFERROR(_xlfn.XLOOKUP(AC10, price_lookup_table!$C:$C, price_lookup_table!$B:$B), "") -> Corporate
A11: LIH | B11: 45677 | C11: 45663 | D11: screening | E11: Booked | F11: Garvey | G11: Spurrett | H11: 87662 Express Parkway | I11: Apt 608 | M11: N16 8BF | N11: gspurrett9@ucoz.ru | O11: male | P11: 21925 | Q11: =DATEDIF(P11,B11,"Y") -> 65 | R11: E999EE4D | S11: 447414893831 | T11: Advanced | V11: {=IFERROR( _xlfn.XLOOKUP(1, (tblPrices[Prefix]=$AC11)*(tblPrices[Product Code]=$T11), tblPrices[Price] ), 0 ) + IF(ISNUMBER(SEARCH("Mammogram",$U11)), IFERROR(_xlfn.XLOOKUP(1,(tblPrices[Prefix]=$AC11)*(tblPrices[Product Code]="Mammogram"),tblPrices[Price]),0), 0 ) + IF(ISNUMBER(SEARCH("PSA",$U11)), IFERROR(_xlfn.XLOOKUP(1,(tblPrices[Prefix]=$AC11)*(tblPrices[Product Code]="PSA"),tblPrices[Price]),0), 0 )} -> 543.38 | W11: dispatched | X11: paid,fasting,online,viewed_online | Z11: 22005957 | AA11: U48 | AB11: {=_xlfn.LET(_xlpm.pc, UPPER(TRIM(M11)), LEFT(_xlpm.pc, MIN(FIND({0,1,2,3,4,5,6,7,8,9}, _xlpm.pc&"0123456789"))-1))} -> N | AC11: U48 | AD11: =VLOOKUP(AB11, postcode_table!A:B, 2, FALSE) -> North London | AE11: =IFERROR(_xlfn.XLOOKUP(AC11, price_lookup_table!$C:$C, price_lookup_table!$B:$B), "") -> Corporate
A12: PRI | B12: 45677 | C12: 45659 | D12: screening | E12: Booked | F12: Carlina | G12: Danielut | H12: 18 Larry Trail | I12: Suite 70 | M12: HR9 7JZ | N12: cdanieluta@cam.ac.uk | O12: male | P12: 34860 | Q12: =DATEDIF(P12,B12,"Y") -> 29 | R12: B5D49A8D | S12: 447787576459 | T12: Advanced Plus | V12: {=IFERROR( _xlfn.XLOOKUP(1, (tblPrices[Prefix]=$AC12)*(tblPrices[Product Code]=$T12), tblPrices[Price] ), 0 ) + IF(ISNUMBER(SEARCH("Mammogram",$U12)), IFERROR(_xlfn.XLOOKUP(1,(tblPrices[Prefix]=$AC12)*(tblPrices[Product Code]="Mammogram"),tblPrices[Price]),0), 0 ) + IF(ISNUMBER(SEARCH("PSA",$U12)), IFERROR(_xlfn.XLOOKUP(1,(tblPrices[Prefix]=$AC12)*(tblPrices[Product Code]="PSA"),tblPrices[Price]),0), 0 )} -> 727.88 | W12: dispatched | X12: paid,fasting,online,viewed_online | Z12: 21517809 | AA12: U48 | AB12: {=_xlfn.LET(_xlpm.pc, UPPER(TRIM(M12)), LEFT(_xlpm.pc, MIN(FIND({0,1,2,3,4,5,6,7,8,9}, _xlpm.pc&"0123456789"))-1))} -> HR | AC12: U48 | AD12: =VLOOKUP(AB12, postcode_table!A:B, 2, FALSE) -> Hereford | AE12: =IFERROR(_xlfn.XLOOKUP(AC12, price_lookup_table!$C:$C, price_lookup_table!$B:$B), "") -> Corporate
A13: BSE | B13: 45678 | C13: 45660 | D13: screening | E13: Booked | F13: Drew | G13: Nollet | H13: 82103 Kipling Trail | I13: Room 278 | M13: CO5 0PX | N13: dnolletb@hc360.com | O13: female | P13: 34065 | Q13: =DATEDIF(P13,B13,"Y") -> 31 | R13: 750DF5E6 | S13: 447803127114 | T13: Advanced | V13: {=IFERROR( _xlfn.XLOOKUP(1, (tblPrices[Prefix]=$AC13)*(tblPrices[Product Code]=$T13), tblPrices[Price] ), 0 ) + IF(ISNUMBER(SEARCH("Mammogram",$U13)), IFERROR(_xlfn.XLOOKUP(1,(tblPrices[Prefix]=$AC13)*(tblPrices[Product Code]="Mammogram"),tblPrices[Price]),0), 0 ) + IF(ISNUMBER(SEARCH("PSA",$U13)), IFERROR(_xlfn.XLOOKUP(1,(tblPrices[Prefix]=$AC13)*(tblPrices[Product Code]="PSA"),tblPrices[Price]),0), 0 )} -> 543.38 | W13: dispatched | X13: paid,fasting,online,viewed_online | Z13: 22003689 | AA13: U48 | AB13: {=_xlfn.LET(_xlpm.pc, UPPER(TRIM(M13)), LEFT(_xlpm.pc, MIN(FIND({0,1,2,3,4,5,6,7,8,9}, _xlpm.pc&"0123456789"))-1))} -> CO | AC13: U48 | AD13: =VLOOKUP(AB13, postcode_table!A:B, 2, FALSE) -> Colchester | AE13: =IFERROR(_xlfn.XLOOKUP(AC13, price_lookup_table!$C:$C, price_lookup_table!$B:$B), "") -> Corporate
A14: BSE | B14: 45678 | C14: 45660 | D14: screening | E14: Booked | F14: Man | G14: De la Yglesia | H14: 83 Holy Cross Lane | I14: PO Box 99290 | M14: CO5 0PX | N14: mdelayglesiac@eepurl.com | O14: male | P14: 23477 | Q14: =DATEDIF(P14,B14,"Y") -> 60 | R14: 94F3FC73 | S14: 447713247692 | T14: Advanced | V14: {=IFERROR( _xlfn.XLOOKUP(1, (tblPrices[Prefix]=$AC14)*(tblPrices[Product Code]=$T14), tblPrices[Price] ), 0 ) + IF(ISNUMBER(SEARCH("Mammogram",$U14)), IFERROR(_xlfn.XLOOKUP(1,(tblPrices[Prefix]=$AC14)*(tblPrices[Product Code]="Mammogram"),tblPrices[Price]),0), 0 ) + IF(ISNUMBER(SEARCH("PSA",$U14)), IFERROR(_xlfn.XLOOKUP(1,(tblPrices[Prefix]=$AC14)*(tblPrices[Product Code]="PSA"),tblPrices[Price]),0), 0 )} -> 543.38 | W14: dispatched | X14: paid,fasting,online,viewed_online | Z14: 22003455 | AA14: U48 | AB14: {=_xlfn.LET(_xlpm.pc, UPPER(TRIM(M14)), LEFT(_xlpm.pc, MIN(FIND({0,1,2,3,4,5,6,7,8,9}, _xlpm.pc&"0123456789"))-1))} -> CO | AC14: U48 | AD14: =VLOOKUP(AB14, postcode_table!A:B, 2, FALSE) -> Colchester | AE14: =IFERROR(_xlfn.XLOOKUP(AC14, price_lookup_table!$C:$C, price_lookup_table!$B:$B), "") -> Corporate
A15: PRI | B15: 45678 | C15: 45670 | D15: screening | E15: Booked | F15: Munmro | G15: Malden | H15: 90 Katie Way | I15: Apt 1246 | M15: GL56 0QT | N15: mmaldend@istockphoto.com | O15: male | P15: 26045 | Q15: =DATEDIF(P15,B15,"Y") -> 53 | R15: 0C9E6F5F | S15: 447880598096 | T15: Advanced | V15: {=IFERROR( _xlfn.XLOOKUP(1, (tblPrices[Prefix]=$AC15)*(tblPrices[Product Code]=$T15), tblPrices[Price] ), 0 ) + IF(ISNUMBER(SEARCH("Mammogram",$U15)), IFERROR(_xlfn.XLOOKUP(1,(tblPrices[Prefix]=$AC15)*(tblPrices[Product Code]="Mammogram"),tblPrices[Price]),0), 0 ) + IF(ISNUMBER(SEARCH("PSA",$U15)), IFERROR(_xlfn.XLOOKUP(1,(tblPrices[Prefix]=$AC15)*(tblPrices[Product Code]="PSA"),tblPrices[Price]),0), 0 )} -> 543.38 | W15: dispatched | X15: rescheduled,paid,fasting,online,viewed_online | Z15: 22007131 | AA15: U48 | AB15: {=_xlfn.LET(_xlpm.pc, UPPER(TRIM(M15)), LEFT(_xlpm.pc, MIN(FIND({0,1,2,3,4,5,6,7,8,9}, _xlpm.pc&"0123456789"))-1))} -> GL | AC15: U48 | AD15: =VLOOKUP(AB15, postcode_table!A:B, 2, FALSE) -> Gloucester | AE15: =IFERROR(_xlfn.XLOOKUP(AC15, price_lookup_table!$C:$C, price_lookup_table!$B:$B), "") -> Corporate
A16: ALV | B16: 45678 | C16: 45670 | D16: screening | E16: Booked | F16: Alli | G16: Jozsika | H16: 00 Sachtjen Terrace | I16: Apt 116 | M16: GU1 2SJ | N16: ajozsikae@youtu.be | O16: female | P16: 16035 | Q16: =DATEDIF(P16,B16,"Y") -> 81 | R16: A9E8B973 | S16: 447523844064 | T16: Essential | V16: {=IFERROR( _xlfn.XLOOKUP(1, (tblPrices[Prefix]=$AC16)*(tblPrices[Product Code]=$T16), tblPrices[Price] ), 0 ) + IF(ISNUMBER(SEARCH("Mammogram",$U16)), IFERROR(_xlfn.XLOOKUP(1,(tblPrices[Prefix]=$AC16)*(tblPrices[Product Code]="Mammogram"),tblPrices[Price]),0), 0 ) + IF(ISNUMBER(SEARCH("PSA",$U16)), IFERROR(_xlfn.XLOOKUP(1,(tblPrices[Prefix]=$AC16)*(tblPrices[Product Code]="PSA"),tblPrices[Price]),0), 0 )} -> 246 | W16: dispatched | X16: paid,phone_call_required,fasting,online,viewed_online | Z16: 22014220 | AA16: M01Phone | AB16: {=_xlfn.LET(_xlpm.pc, UPPER(TRIM(M16)), LEFT(_xlpm.pc, MIN(FIND({0,1,2,3,4,5,6,7,8,9}, _xlpm.pc&"0123456789"))-1))} -> GU | AC16: =LEFT(AA16, 3) -> M01 | AD16: =VLOOKUP(AB16, postcode_table!A:B, 2, FALSE) -> Guildford | AE16: =IFERROR(_xlfn.XLOOKUP(AC16, price_lookup_table!$C:$C, price_lookup_table!$B:$B), "") -> Self Pay
A17: ALX | B17: 45678 | C17: 45670 | D17: screening | E17: Booked | F17: Flossy | G17: Osban | H17: 97648 Forest Dale Parkway | I17: Suite 89 | M17: M40 8BW | N17: fosbanf@surveymonkey.com | O17: male | P17: 27129 | Q17: =DATEDIF(P17,B17,"Y") -> 50 | R17: 1AAAB80A | S17: 447920884410 | T17: Essential | V17: {=IFERROR( _xlfn.XLOOKUP(1, (tblPrices[Prefix]=$AC17)*(tblPrices[Product Code]=$T17), tblPrices[Price] ), 0 ) + IF(ISNUMBER(SEARCH("Mammogram",$U17)), IFERROR(_xlfn.XLOOKUP(1,(tblPrices[Prefix]=$AC17)*(tblPrices[Product Code]="Mammogram"),tblPrices[Price]),0), 0 ) + IF(ISNUMBER(SEARCH("PSA",$U17)), IFERROR(_xlfn.XLOOKUP(1,(tblPrices[Prefix]=$AC17)*(tblPrices[Product Code]="PSA"),tblPrices[Price]),0), 0 )} -> 246 | W17: dispatched | X17: rescheduled,paid,fasting,online,viewed_online | Z17: 22008655 | AA17: M01Phone | AB17: {=_xlfn.LET(_xlpm.pc, UPPER(TRIM(M17)), LEFT(_xlpm.pc, MIN(FIND({0,1,2,3,4,5,6,7,8,9}, _xlpm.pc&"0123456789"))-1))} -> M | AC17: =LEFT(AA17, 3) -> M01 | AD17: =VLOOKUP(AB17, postcode_table!A:B, 2, FALSE) -> Manchester | AE17: =IFERROR(_xlfn.XLOOKUP(AC17, price_lookup_table!$C:$C, price_lookup_table!$B:$B), "") -> Self Pay
A18: LIH | B18: 45679 | C18: 45660 | D18: screening | E18: Booked | F18: Felic | G18: Sparshutt | H18: 2 Park Meadow Lane | I18: Suite 94 | M18: E1 5FZ | N18: fsparshuttg@wsj.com | O18: male | P18: 35387 | Q18: =DATEDIF(P18,B18,"Y") -> 28 | R18: AA32E553 | S18: 447798893954 | T18: Advanced | V18: {=IFERROR( _xlfn.XLOOKUP(1, (tblPrices[Prefix]=$AC18)*(tblPrices[Product Code]=$T18), tblPrices[Price] ), 0 ) + IF(ISNUMBER(SEARCH("Mammogram",$U18)), IFERROR(_xlfn.XLOOKUP(1,(tblPrices[Prefix]=$AC18)*(tblPrices[Product Code]="Mammogram"),tblPrices[Price]),0), 0 ) + IF(ISNUMBER(SEARCH("PSA",$U18)), IFERROR(_xlfn.XLOOKUP(1,(tblPrices[Prefix]=$AC18)*(tblPrices[Product Code]="PSA"),tblPrices[Price]),0), 0 )} -> 543 | W18: dispatched | X18: paid,fasting,online,viewed_online | Z18: 22002551 | AA18: AXAMEMBER | AB18: {=_xlfn.LET(_xlpm.pc, UPPER(TRIM(M18)), LEFT(_xlpm.pc, MIN(FIND({0,1,2,3,4,5,6,7,8,9}, _xlpm.pc&"0123456789"))-1))} -> E | AC18: =LEFT(AA18, 3) -> AXA | AD18: =VLOOKUP(AB18, postcode_table!A:B, 2, FALSE) -> East London | AE18: =IFERROR(_xlfn.XLOOKUP(AC18, price_lookup_table!$C:$C, price_lookup_table!$B:$B), "") -> Self Pay
A19: LIH | B19: 45679 | C19: 45667 | D19: screening | E19: Booked | F19: Vince | G19: Stoyle | H19: 6 Truax Crossing | I19: PO Box 88818 | M19: SE10 8AS | N19: vstoyleh@typepad.com | O19: male | P19: 27524 | Q19: =DATEDIF(P19,B19,"Y") -> 49 | R19: 7E600672 | S19: 447826855190 | T19: Advanced | V19: {=IFERROR( _xlfn.XLOOKUP(1, (tblPrices[Prefix]=$AC19)*(tblPrices[Product Code]=$T19), tblPrices[Price] ), 0 ) + IF(ISNUMBER(SEARCH("Mammogram",$U19)), IFERROR(_xlfn.XLOOKUP(1,(tblPrices[Prefix]=$AC19)*(tblPrices[Product Code]="Mammogram"),tblPrices[Price]),0), 0 ) + IF(ISNUMBER(SEARCH("PSA",$U19)), IFERROR(_xlfn.XLOOKUP(1,(tblPrices[Prefix]=$AC19)*(tblPrices[Product Code]="PSA"),tblPrices[Price]),0), 0 )} -> 543 | W19: dispatched | X19: rescheduled,paid,fasting,online,viewed_online | Z19: 21159036 | AA19: AXAMEMBER | AB19: {=_xlfn.LET(_xlpm.pc, UPPER(TRIM(M19)), LEFT(_xlpm.pc, MIN(FIND({0,1,2,3,4,5,6,7,8,9}, _xlpm.pc&"0123456789"))-1))} -> SE | AC19: =LEFT(AA19, 3) -> AXA | AD19: =VLOOKUP(AB19, postcode_table!A:B, 2, FALSE) -> South East London | AE19: =IFERROR(_xlfn.XLOOKUP(AC19, price_lookup_table!$C:$C, price_lookup_table!$B:$B), "") -> Self Pay
A20: SYC | B20: 45679 | C20: 45659 | D20: screening | E20: Booked | F20: Ulrick | G20: Swedeland | H20: 71132 Nobel Road | I20: PO Box 84101 | M20: SW6 6QA | N20: uswedelandi@sciencedaily.com | O20: male | P20: 17343 | Q20: =DATEDIF(P20,B20,"Y") -> 77 | R20: 13090BEF | S20: 447436338092 | T20: Advanced | V20: {=IFERROR( _xlfn.XLOOKUP(1, (tblPrices[Prefix]=$AC20)*(tblPrices[Product Code]=$T20), tblPrices[Price] ), 0 ) + IF(ISNUMBER(SEARCH("Mammogram",$U20)), IFERROR(_xlfn.XLOOKUP(1,(tblPrices[Prefix]=$AC20)*(tblPrices[Product Code]="Mammogram"),tblPrices[Price]),0), 0 ) + IF(ISNUMBER(SEARCH("PSA",$U20)), IFERROR(_xlfn.XLOOKUP(1,(tblPrices[Prefix]=$AC20)*(tblPrices[Product Code]="PSA"),tblPrices[Price]),0), 0 )} -> 543 | W20: dispatched | X20: paid,fasting,online,viewed_online | Z20: 22001140 | AA20: AXAMEMBER | AB20: {=_xlfn.LET(_xlpm.pc, UPPER(TRIM(M20)), LEFT(_xlpm.pc, MIN(FIND({0,1,2,3,4,5,6,7,8,9}, _xlpm.pc&"0123456789"))-1))} -> SW | AC20: =LEFT(AA20, 3) -> AXA | AD20: =VLOOKUP(AB20, postcode_table!A:B, 2, FALSE) -> South West London | AE20: =IFERROR(_xlfn.XLOOKUP(AC20, price_lookup_table!$C:$C, price_lookup_table!$B:$B), "") -> Self Pay
A21: BTH | B21: 45679 | C21: 45670 | D21: screening | E21: Booked | F21: Georgine | G21: Berre | H21: 26 Fordem Junction | I21: 1st Floor | M21: BA1 2PH | N21: gberrej@wired.com | O21: female | P21: 24020 | Q21: =DATEDIF(P21,B21,"Y") -> 59 | R21: 59DB436B | S21: 447810810402 | T21: Advanced | V21: {=IFERROR( _xlfn.XLOOKUP(1, (tblPrices[Prefix]=$AC21)*(tblPrices[Product Code]=$T21), tblPrices[Price] ), 0 ) + IF(ISNUMBER(SEARCH("Mammogram",$U21)), IFERROR(_xlfn.XLOOKUP(1,(tblPrices[Prefix]=$AC21)*(tblPrices[Product Code]="Mammogram"),tblPrices[Price]),0), 0 ) + IF(ISNUMBER(SEARCH("PSA",$U21)), IFERROR(_xlfn.XLOOKUP(1,(tblPrices[Prefix]=$AC21)*(tblPrices[Product Code]="PSA"),tblPrices[Price]),0), 0 )} -> 724.5 | W21: dispatched | X21: viewed_online,paid,fasting,online,ecg_uploaded | Z21: 20941152 | AA21: M01Phone | AB21: {=_xlfn.LET(_xlpm.pc, UPPER(TRIM(M21)), LEFT(_xlpm.pc, MIN(FIND({0,1,2,3,4,5,6,7,8,9}, _xlpm.pc&"0123456789"))-1))} -> BA | AC21: =LEFT(AA21, 3) -> M01 | AD21: =VLOOKUP(AB21, postcode_table!A:B, 2, FALSE) -> Bath | AE21: =IFERROR(_xlfn.XLOOKUP(AC21, price_lookup_table!$C:$C, price_lookup_table!$B:$B), "") -> Self Pay
A22: ALV | B22: 45679 | C22: 45664 | D22: screening | E22: Booked | F22: Kermie | G22: Snodin | H22: 488 Talisman Hill | I22: Room 885 | M22: SL5 7PF | N22: ksnodink@mediafire.com | O22: male | P22: 16831 | Q22: =DATEDIF(P22,B22,"Y") -> 78 | R22: 5FBC9C1A | S22: 447775816261 | T22: Advanced | V22: {=IFERROR( _xlfn.XLOOKUP(1, (tblPrices[Prefix]=$AC22)*(tblPrices[Product Code]=$T22), tblPrices[Price] ), 0 ) + IF(ISNUMBER(SEARCH("Mammogram",$U22)), IFERROR(_xlfn.XLOOKUP(1,(tblPrices[Prefix]=$AC22)*(tblPrices[Product Code]="Mammogram"),tblPrices[Price]),0), 0 ) + IF(ISNUMBER(SEARCH("PSA",$U22)), IFERROR(_xlfn.XLOOKUP(1,(tblPrices[Prefix]=$AC22)*(tblPrices[Product Code]="PSA"),tblPrices[Price]),0), 0 )} -> 517.5 | W22: dispatched | X22: paid,fasting,online,ecg_uploaded,viewed_online | Z22: 19086541 | AA22: T71 | AB22: {=_xlfn.LET(_xlpm.pc, UPPER(TRIM(M22)), LEFT(_xlpm.pc, MIN(FIND({0,1,2,3,4,5,6,7,8,9}, _xlpm.pc&"0123456789"))-1))} -> SL | AC22: T71 | AD22: =VLOOKUP(AB22, postcode_table!A:B, 2, FALSE) -> Slough | AE22: =IFERROR(_xlfn.XLOOKUP(AC22, price_lookup_table!$C:$C, price_lookup_table!$B:$B), "") -> Corporate
A23: RID | B23: 45680 | C23: 45671 | D23: screening | E23: Booked | F23: Arri | G23: Stollenbecker | H23: 511 Melvin Hill | I23: Room 1639 | M23: BS27 3GL | N23: astollenbeckerl@plala.or.jp | O23: male | P23: 16146 | Q23: =DATEDIF(P23,B23,"Y") -> 80 | R23: 204EFB6E | S23: 447776410747 | T23: Advanced | V23: {=IFERROR( _xlfn.XLOOKUP(1, (tblPrices[Prefix]=$AC23)*(tblPrices[Product Code]=$T23), tblPrices[Price] ), 0 ) + IF(ISNUMBER(SEARCH("Mammogram",$U23)), IFERROR(_xlfn.XLOOKUP(1,(tblPrices[Prefix]=$AC23)*(tblPrices[Product Code]="Mammogram"),tblPrices[Price]),0), 0 ) + IF(ISNUMBER(SEARCH("PSA",$U23)), IFERROR(_xlfn.XLOOKUP(1,(tblPrices[Prefix]=$AC23)*(tblPrices[Product Code]="PSA"),tblPrices[Price]),0), 0 )} -> 517.5 | W23: dispatched | X23: paid,fasting,online,viewed_online | Z23: 22016359 | AA23: T71 | AB23: {=_xlfn.LET(_xlpm.pc, UPPER(TRIM(M23)), LEFT(_xlpm.pc, MIN(FIND({0,1,2,3,4,5,6,7,8,9}, _xlpm.pc&"0123456789"))-1))} -> BS | AC23: T71 | AD23: =VLOOKUP(AB23, postcode_table!A:B, 2, FALSE) -> Bristol | AE23: =IFERROR(_xlfn.XLOOKUP(AC23, price_lookup_table!$C:$C, price_lookup_table!$B:$B), "") -> Corporate
A24: GAR | B24: 45680 | C24: 45674 | D24: screening | E24: Booked | F24: Kimmie | G24: Vince | H24: 799 Hayes Drive | I24: Room 1685 | M24: HA5 5HX | N24: kvincem@fema.gov | O24: female | P24: 17688 | Q24: =DATEDIF(P24,B24,"Y") -> 76 | R24: 1BC710C0 | S24: 447967366230 | T24: Advanced | V24: {=IFERROR( _xlfn.XLOOKUP(1, (tblPrices[Prefix]=$AC24)*(tblPrices[Product Code]=$T24), tblPrices[Price] ), 0 ) + IF(ISNUMBER(SEARCH("Mammogram",$U24)), IFERROR(_xlfn.XLOOKUP(1,(tblPrices[Prefix]=$AC24)*(tblPrices[Product Code]="Mammogram"),tblPrices[Price]),0), 0 ) + IF(ISNUMBER(SEARCH("PSA",$U24)), IFERROR(_xlfn.XLOOKUP(1,(tblPrices[Prefix]=$AC24)*(tblPrices[Product Code]="PSA"),tblPrices[Price]),0), 0 )} -> 517.5 | W24: dispatched | X24: viewed_online,paid,fasting,green,online | Z24: 16696280 | AA24: T71 | AB24: {=_xlfn.LET(_xlpm.pc, UPPER(TRIM(M24)), LEFT(_xlpm.pc, MIN(FIND({0,1,2,3,4,5,6,7,8,9}, _xlpm.pc&"0123456789"))-1))} -> HA | AC24: T71 | AD24: =VLOOKUP(AB24, postcode_table!A:B, 2, FALSE) -> Harrow | AE24: =IFERROR(_xlfn.XLOOKUP(AC24, price_lookup_table!$C:$C, price_lookup_table!$B:$B), "") -> Corporate
A25: RUN | B25: 45680 | C25: 45663 | D25: screening | E25: Booked | F25: Ludovika | G25: Botwood | H25: 8 Westend Alley | I25: PO Box 62728 | M25: TW11 9HQ | N25: lbotwoodn@digg.com | O25: female | P25: 26916 | Q25: =DATEDIF(P25,B25,"Y") -> 51 | R25: A7A2D9D7 | S25: 447957371753 | T25: Advanced Plus | V25: {=IFERROR( _xlfn.XLOOKUP(1, (tblPrices[Prefix]=$AC25)*(tblPrices[Product Code]=$T25), tblPrices[Price] ), 0 ) + IF(ISNUMBER(SEARCH("Mammogram",$U25)), IFERROR(_xlfn.XLOOKUP(1,(tblPrices[Prefix]=$AC25)*(tblPrices[Product Code]="Mammogram"),tblPrices[Price]),0), 0 ) + IF(ISNUMBER(SEARCH("PSA",$U25)), IFERROR(_xlfn.XLOOKUP(1,(tblPrices[Prefix]=$AC25)*(tblPrices[Product Code]="PSA"),tblPrices[Price]),0), 0 )} -> 693.38 | W25: dispatched | X25: paid,fasting,amber,online,ecg_uploaded,viewed_online | Z25: 22004414 | AA25: T71 | AB25: {=_xlfn.LET(_xlpm.pc, UPPER(TRIM(M25)), LEFT(_xlpm.pc, MIN(FIND({0,1,2,3,4,5,6,7,8,9}, _xlpm.pc&"0123456789"))-1))} -> TW | AC25: T71 | AD25: =VLOOKUP(AB25, postcode_table!A:B, 2, FALSE) -> Twickenham | AE25: =IFERROR(_xlfn.XLOOKUP(AC25, price_lookup_table!$C:$C, price_lookup_table!$B:$B), "") -> Corporate
A26: RHB | B26: 45680 | C26: 45677 | D26: screening | E26: Booked | F26: Fairleigh | G26: Sadlier | H26: 2 6th Lane | I26: 14th Floor | M26: IV2 5AZ | N26: fsadliero@github.com | O26: male | P26: 27291 | Q26: =DATEDIF(P26,B26,"Y") -> 50 | R26: 0BB10AE6 | S26: 447801289103 | T26: Advanced | V26: {=IFERROR( _xlfn.XLOOKUP(1, (tblPrices[Prefix]=$AC26)*(tblPrices[Product Code]=$T26), tblPrices[Price] ), 0 ) + IF(ISNUMBER(SEARCH("Mammogram",$U26)), IFERROR(_xlfn.XLOOKUP(1,(tblPrices[Prefix]=$AC26)*(tblPrices[Product Code]="Mammogram"),tblPrices[Price]),0), 0 ) + IF(ISNUMBER(SEARCH("PSA",$U26)), IFERROR(_xlfn.XLOOKUP(1,(tblPrices[Prefix]=$AC26)*(tblPrices[Product Code]="PSA"),tblPrices[Price]),0), 0 )} -> 517.5 | W26: dispatched | X26: paid,phone_call_required,fasting,online,ecg_uploaded,viewed_online | Z26: 18668675 | AA26: T71 | AB26: {=_xlfn.LET(_xlpm.pc, UPPER(TRIM(M26)), LEFT(_xlpm.pc, MIN(FIND({0,1,2,3,4,5,6,7,8,9}, _xlpm.pc&"0123456789"))-1))} -> IV | AC26: T71 | AD26: =VLOOKUP(AB26, postcode_table!A:B, 2, FALSE) -> Inverness | AE26: =IFERROR(_xlfn.XLOOKUP(AC26, price_lookup_table!$C:$C, price_lookup_table!$B:$B), "") -> Corporate
A27: GAR | B27: 45681 | C27: 45674 | D27: screening | E27: Booked | F27: Nickola | G27: McKeaney | H27: 4 Stephen Alley | I27: Apt 1786 | M27: HA5 5HX | N27: nmckeaneyp@goo.ne.jp | O27: male | P27: 35531 | Q27: =DATEDIF(P27,B27,"Y") -> 27 | R27: 1020473D | S27: 447973819691 | T27: Advanced | V27: {=IFERROR( _xlfn.XLOOKUP(1, (tblPrices[Prefix]=$AC27)*(tblPrices[Product Code]=$T27), tblPrices[Price] ), 0 ) + IF(ISNUMBER(SEARCH("Mammogram",$U27)), IFERROR(_xlfn.XLOOKUP(1,(tblPrices[Prefix]=$AC27)*(tblPrices[Product Code]="Mammogram"),tblPrices[Price]),0), 0 ) + IF(ISNUMBER(SEARCH("PSA",$U27)), IFERROR(_xlfn.XLOOKUP(1,(tblPrices[Prefix]=$AC27)*(tblPrices[Product Code]="PSA"),tblPrices[Price]),0), 0 )} -> 517.5 | W27: dispatched | X27: rescheduled,paid,fasting,amber,online,viewed_online | Z27: 16005325 | AA27: T71 | AB27: {=_xlfn.LET(_xlpm.pc, UPPER(TRIM(M27)), LEFT(_xlpm.pc, MIN(FIND({0,1,2,3,4,5,6,7,8,9}, _xlpm.pc&"0123456789"))-1))} -> HA | AC27: T71 | AD27: =VLOOKUP(AB27, postcode_table!A:B, 2, FALSE) -> Harrow | AE27: =IFERROR(_xlfn.XLOOKUP(AC27, price_lookup_table!$C:$C, price_lookup_table!$B:$B), "") -> Corporate
A28: ALX | B28: 45681 | C28: 45663 | D28: screening | E28: Booked | F28: Kirsten | G28: Stogill | H28: 871 Coolidge Park | I28: Suite 28 | M28: WA16 8EJ | N28: kstogillq@slashdot.org | O28: male | P28: 26970 | Q28: =DATEDIF(P28,B28,"Y") -> 51 | R28: 82EFDEB8 | S28: 447904092231 | T28: Advanced | V28: {=IFERROR( _xlfn.XLOOKUP(1, (tblPrices[Prefix]=$AC28)*(tblPrices[Product Code]=$T28), tblPrices[Price] ), 0 ) + IF(ISNUMBER(SEARCH("Mammogram",$U28)), IFERROR(_xlfn.XLOOKUP(1,(tblPrices[Prefix]=$AC28)*(tblPrices[Product Code]="Mammogram"),tblPrices[Price]),0), 0 ) + IF(ISNUMBER(SEARCH("PSA",$U28)), IFERROR(_xlfn.XLOOKUP(1,(tblPrices[Prefix]=$AC28)*(tblPrices[Product Code]="PSA"),tblPrices[Price]),0), 0 )} -> 517.5 | W28: dispatched | X28: paid,fasting,online,ecg_uploaded,viewed_online | Z28: 16916934 | AA28: T71 | AB28: {=_xlfn.LET(_xlpm.pc, UPPER(TRIM(M28)), LEFT(_xlpm.pc, MIN(FIND({0,1,2,3,4,5,6,7,8,9}, _xlpm.pc&"0123456789"))-1))} -> WA | AC28: T71 | AD28: =VLOOKUP(AB28, postcode_table!A:B, 2, FALSE) -> Warrington | AE28: =IFERROR(_xlfn.XLOOKUP(AC28, price_lookup_table!$C:$C, price_lookup_table!$B:$B), "") -> Corporate
A29: ALB | B29: 45681 | C29: 45665 | D29: screening | E29: Booked | F29: Fabe | G29: Agdahl | H29: 1749 Jana Point | I29: Suite 45 | M29: AB15 8GW | N29: fagdahlr@alibaba.com | O29: male | P29: 28663 | Q29: =DATEDIF(P29,B29,"Y") -> 46 | R29: F01C8028 | S29: 447865198512 | T29: Advanced | V29: {=IFERROR( _xlfn.XLOOKUP(1, (tblPrices[Prefix]=$AC29)*(tblPrices[Product Code]=$T29), tblPrices[Price] ), 0 ) + IF(ISNUMBER(SEARCH("Mammogram",$U29)), IFERROR(_xlfn.XLOOKUP(1,(tblPrices[Prefix]=$AC29)*(tblPrices[Product Code]="Mammogram"),tblPrices[Price]),0), 0 ) + IF(ISNUMBER(SEARCH("PSA",$U29)), IFERROR(_xlfn.XLOOKUP(1,(tblPrices[Prefix]=$AC29)*(tblPrices[Product Code]="PSA"),tblPrices[Price]),0), 0 )} -> 517.5 | W29: dispatched | X29: paid,fasting | Z29: 20618377 | AA29: T71 | AB29: {=_xlfn.LET(_xlpm.pc, UPPER(TRIM(M29)), LEFT(_xlpm.pc, MIN(FIND({0,1,2,3,4,5,6,7,8,9}, _xlpm.pc&"0123456789"))-1))} -> AB | AC29: T71 | AD29: =VLOOKUP(AB29, postcode_table!A:B, 2, FALSE) -> Aberdeen | AE29: =IFERROR(_xlfn.XLOOKUP(AC29, price_lookup_table!$C:$C, price_lookup_table!$B:$B), "") -> Corporate
A30: SLO | B30: 45684 | C30: 45659 | D30: screening | E30: Booked | F30: Redford | G30: Charnock | H30: 333 Kingsford Alley | I30: 15th Floor | M30: CR3 6JF | N30: rcharnocks@bbc.co.uk | O30: male | P30: 36810 | Q30: =DATEDIF(P30,B30,"Y") -> 24 | R30: 07452CA1 | S30: 447724255886 | T30: Advanced | V30: {=IFERROR( _xlfn.XLOOKUP(1, (tblPrices[Prefix]=$AC30)*(tblPrices[Product Code]=$T30), tblPrices[Price] ), 0 ) + IF(ISNUMBER(SEARCH("Mammogram",$U30)), IFERROR(_xlfn.XLOOKUP(1,(tblPrices[Prefix]=$AC30)*(tblPrices[Product Code]="Mammogram"),tblPrices[Price]),0), 0 ) + IF(ISNUMBER(SEARCH("PSA",$U30)), IFERROR(_xlfn.XLOOKUP(1,(tblPrices[Prefix]=$AC30)*(tblPrices[Product Code]="PSA"),tblPrices[Price]),0), 0 )} -> 517.5 | W30: dispatched | X30: rescheduled,paid,fasting,online,viewed_online | Z30: 21561378 | AA30: T71 | AB30: {=_xlfn.LET(_xlpm.pc, UPPER(TRIM(M30)), LEFT(_xlpm.pc, MIN(FIND({0,1,2,3,4,5,6,7,8,9}, _xlpm.pc&"0123456789"))-1))} -> CR | AC30: T71 | AD30: =VLOOKUP(AB30, postcode_table!A:B, 2, FALSE) -> Croydon | AE30: =IFERROR(_xlfn.XLOOKUP(AC30, price_lookup_table!$C:$C, price_lookup_table!$B:$B), "") -> Corporate
A31: LIH | B31: 45684 | C31: 45664 | D31: screening | E31: Booked | F31: Artemus | G31: Teacy | H31: 363 Ramsey Trail | I31: PO Box 48667 | M31: EC1M 5UG | N31: ateacyt@g.co | O31: male | P31: 15933 | Q31: =DATEDIF(P31,B31,"Y") -> 81 | R31: 09D45ABC | S31: 447741766348 | T31: Advanced | V31: {=IFERROR( _xlfn.XLOOKUP(1, (tblPrices[Prefix]=$AC31)*(tblPrices[Product Code]=$T31), tblPrices[Price] ), 0 ) + IF(ISNUMBER(SEARCH("Mammogram",$U31)), IFERROR(_xlfn.XLOOKUP(1,(tblPrices[Prefix]=$AC31)*(tblPrices[Product Code]="Mammogram"),tblPrices[Price]),0), 0 ) + IF(ISNUMBER(SEARCH("PSA",$U31)), IFERROR(_xlfn.XLOOKUP(1,(tblPrices[Prefix]=$AC31)*(tblPrices[Product Code]="PSA"),tblPrices[Price]),0), 0 )} -> 517.5 | W31: dispatched | X31: paid,fasting,online,viewed_online | Z31: 22007237 | AA31: T71 | AB31: {=_xlfn.LET(_xlpm.pc, UPPER(TRIM(M31)), LEFT(_xlpm.pc, MIN(FIND({0,1,2,3,4,5,6,7,8,9}, _xlpm.pc&"0123456789"))-1))} -> EC | AC31: T71 | AD31: =VLOOKUP(AB31, postcode_table!A:B, 2, FALSE) -> East Central London | AE31: =IFERROR(_xlfn.XLOOKUP(AC31, price_lookup_table!$C:$C, price_lookup_table!$B:$B), "") -> Corporate
A32: MNR | B32: 45684 | C32: 45660 | D32: screening | E32: Booked | F32: Ferdinande | G32: Jozaitis | H32: 5 Brown Parkway | I32: Suite 68 | M32: SG4 9PN | N32: fjozaitisu@topsy.com | O32: female | P32: 35439 | Q32: =DATEDIF(P32,B32,"Y") -> 28 | R32: 5F17E637 | S32: 447881658156 | T32: Advanced | V32: {=IFERROR( _xlfn.XLOOKUP(1, (tblPrices[Prefix]=$AC32)*(tblPrices[Product Code]=$T32), tblPrices[Price] ), 0 ) + IF(ISNUMBER(SEARCH("Mammogram",$U32)), IFERROR(_xlfn.XLOOKUP(1,(tblPrices[Prefix]=$AC32)*(tblPrices[Product Code]="Mammogram"),tblPrices[Price]),0), 0 ) + IF(ISNUMBER(SEARCH("PSA",$U32)), IFERROR(_xlfn.XLOOKUP(1,(tblPrices[Prefix]=$AC32)*(tblPrices[Product Code]="PSA"),tblPrices[Price]),0), 0 )} -> 543 | W32: dispatched | X32: paid,fasting,online,ecg_uploaded,viewed_online | Z32: 22003699 | AA32: AXAMEMBER | AB32: {=_xlfn.LET(_xlpm.pc, UPPER(TRIM(M32)), LEFT(_xlpm.pc, MIN(FIND({0,1,2,3,4,5,6,7,8,9}, _xlpm.pc&"0123456789"))-1))} -> SG | AC32: =LEFT(AA32, 3) -> AXA | AD32: =VLOOKUP(AB32, postcode_table!A:B, 2, FALSE) -> Stevenage | AE32: =IFERROR(_xlfn.XLOOKUP(AC32, price_lookup_table!$C:$C, price_lookup_table!$B:$B), "") -> Self Pay
A33: MNR | B33: 45684 | C33: 45660 | D33: screening | E33: Booked | F33: Manuel | G33: De Malchar | H33: 6 Northwestern Place | I33: Room 1879 | M33: SG4 9PN | N33: mdemalcharv@admin.ch | O33: male | P33: 31882 | Q33: =DATEDIF(P33,B33,"Y") -> 37 | R33: A2781577 | S33: 447890316923 | T33: Advanced | V33: {=IFERROR( _xlfn.XLOOKUP(1, (tblPrices[Prefix]=$AC33)*(tblPrices[Product Code]=$T33), tblPrices[Price] ), 0 ) + IF(ISNUMBER(SEARCH("Mammogram",$U33)), IFERROR(_xlfn.XLOOKUP(1,(tblPrices[Prefix]=$AC33)*(tblPrices[Product Code]="Mammogram"),tblPrices[Price]),0), 0 ) + IF(ISNUMBER(SEARCH("PSA",$U33)), IFERROR(_xlfn.XLOOKUP(1,(tblPrices[Prefix]=$AC33)*(tblPrices[Product Code]="PSA"),tblPrices[Price]),0), 0 )} -> 543 | W33: dispatched | X33: paid,fasting,online,ecg_uploaded,viewed_online | Z33: 22003190 | AA33: AXAMEMBER | AB33: {=_xlfn.LET(_xlpm.pc, UPPER(TRIM(M33)), LEFT(_xlpm.pc, MIN(FIND({0,1,2,3,4,5,6,7,8,9}, _xlpm.pc&"0123456789"))-1))} -> SG | AC33: =LEFT(AA33, 3) -> AXA | AD33: =VLOOKUP(AB33, postcode_table!A:B, 2, FALSE) -> Stevenage | AE33: =IFERROR(_xlfn.XLOOKUP(AC33, price_lookup_table!$C:$C, price_lookup_table!$B:$B), "") -> Self Pay
A34: SYC | B34: 45684 | C34: 45671 | D34: screening | E34: Booked | F34: Sascha | G34: Syde | H34: 4868 Vidon Park | I34: Suite 38 | M34: W12 9RZ | N34: ssydew@google.es | O34: female | P34: 15487 | Q34: =DATEDIF(P34,B34,"Y") -> 82 | R34: A2B1E98C | S34: 447947157800 | T34: Advanced | V34: {=IFERROR( _xlfn.XLOOKUP(1, (tblPrices[Prefix]=$AC34)*(tblPrices[Product Code]=$T34), tblPrices[Price] ), 0 ) + IF(ISNUMBER(SEARCH("Mammogram",$U34)), IFERROR(_xlfn.XLOOKUP(1,(tblPrices[Prefix]=$AC34)*(tblPrices[Product Code]="Mammogram"),tblPrices[Price]),0), 0 ) + IF(ISNUMBER(SEARCH("PSA",$U34)), IFERROR(_xlfn.XLOOKUP(1,(tblPrices[Prefix]=$AC34)*(tblPrices[Product Code]="PSA"),tblPrices[Price]),0), 0 )} -> 507.53 | W34: dispatched | X34: rescheduled,paid,fasting,red,online,viewed_online | Z34: 22003140 | AA34: T35 | AB34: {=_xlfn.LET(_xlpm.pc, UPPER(TRIM(M34)), LEFT(_xlpm.pc, MIN(FIND({0,1,2,3,4,5,6,7,8,9}, _xlpm.pc&"0123456789"))-1))} -> W | AC34: T35 | AD34: =VLOOKUP(AB34, postcode_table!A:B, 2, FALSE) -> West London | AE34: =IFERROR(_xlfn.XLOOKUP(AC34, price_lookup_table!$C:$C, price_lookup_table!$B:$B), "") -> Corporate Flex
A35: ALV | B35: 45684 | C35: 45678 | D35: screening | E35: Booked | F35: Reid | G35: Aizlewood | H35: 6702 Sugar Plaza | I35: Room 855 | M35: GU34 3AW | N35: raizlewoodx@bing.com | O35: male | P35: 32387 | Q35: =DATEDIF(P35,B35,"Y") -> 36 | R35: 537FD23A | S35: 447774295485 | T35: Advanced Plus | V35: {=IFERROR( _xlfn.XLOOKUP(1, (tblPrices[Prefix]=$AC35)*(tblPrices[Product Code]=$T35), tblPrices[Price] ), 0 ) + IF(ISNUMBER(SEARCH("Mammogram",$U35)), IFERROR(_xlfn.XLOOKUP(1,(tblPrices[Prefix]=$AC35)*(tblPrices[Product Code]="Mammogram"),tblPrices[Price]),0), 0 ) + IF(ISNUMBER(SEARCH("PSA",$U35)), IFERROR(_xlfn.XLOOKUP(1,(tblPrices[Prefix]=$AC35)*(tblPrices[Product Code]="PSA"),tblPrices[Price]),0), 0 )} -> 0 | W35: dispatched | X35: viewed_online,paid,fasting,online,ecg_uploaded | Z35: 19092667 | AA35: T35 | AB35: {=_xlfn.LET(_xlpm.pc, UPPER(TRIM(M35)), LEFT(_xlpm.pc, MIN(FIND({0,1,2,3,4,5,6,7,8,9}, _xlpm.pc&"0123456789"))-1))} -> GU | AC35: T35 | AD35: =VLOOKUP(AB35, postcode_table!A:B, 2, FALSE) -> Guildford | AE35: =IFERROR(_xlfn.XLOOKUP(AC35, price_lookup_table!$C:$C, price_lookup_table!$B:$B), "") -> Corporate Flex
A36: ALV | B36: 45684 | C36: 45659 | D36: screening | E36: Booked | F36: Fenelia | G36: Blaszczynski | H36: 015 Hollow Ridge Trail | I36: 13th Floor | M36: GU3 2BZ | N36: fblaszczynskiy@tamu.edu | O36: male | P36: 36214 | Q36: =DATEDIF(P36,B36,"Y") -> 25 | R36: 71F5D986 | S36: 447949399963 | T36: Advanced Plus | V36: {=IFERROR( _xlfn.XLOOKUP(1, (tblPrices[Prefix]=$AC36)*(tblPrices[Product Code]=$T36), tblPrices[Price] ), 0 ) + IF(ISNUMBER(SEARCH("Mammogram",$U36)), IFERROR(_xlfn.XLOOKUP(1,(tblPrices[Prefix]=$AC36)*(tblPrices[Product Code]="Mammogram"),tblPrices[Price]),0), 0 ) + IF(ISNUMBER(SEARCH("PSA",$U36)), IFERROR(_xlfn.XLOOKUP(1,(tblPrices[Prefix]=$AC36)*(tblPrices[Product Code]="PSA"),tblPrices[Price]),0), 0 )} -> 0 | W36: dispatched | X36: paid,fasting,amber,online,ecg_uploaded,viewed_online | Z36: 20595991 | AA36: T35 | AB36: {=_xlfn.LET(_xlpm.pc, UPPER(TRIM(M36)), LEFT(_xlpm.pc, MIN(FIND({0,1,2,3,4,5,6,7,8,9}, _xlpm.pc&"0123456789"))-1))} -> GU | AC36: T35 | AD36: =VLOOKUP(AB36, postcode_table!A:B, 2, FALSE) -> Guildford | AE36: =IFERROR(_xlfn.XLOOKUP(AC36, price_lookup_table!$C:$C, price_lookup_table!$B:$B), "") -> Corporate Flex
A37: CHI | B37: 45684 | C37: 45678 | D37: screening | E37: Booked | F37: Rosalie | G37: Berriman | H37: 06 6th Lane | I37: PO Box 75460 | M37: SL6 6SG | N37: rberrimanz@harvard.edu | O37: female | P37: 23348 | Q37: =DATEDIF(P37,B37,"Y") -> 61 | R37: 229203DC | S37: 447823559000 | T37: Advanced | V37: {=IFERROR( _xlfn.XLOOKUP(1, (tblPrices[Prefix]=$AC37)*(tblPrices[Product Code]=$T37), tblPrices[Price] ), 0 ) + IF(ISNUMBER(SEARCH("Mammogram",$U37)), IFERROR(_xlfn.XLOOKUP(1,(tblPrices[Prefix]=$AC37)*(tblPrices[Product Code]="Mammogram"),tblPrices[Price]),0), 0 ) + IF(ISNUMBER(SEARCH("PSA",$U37)), IFERROR(_xlfn.XLOOKUP(1,(tblPrices[Prefix]=$AC37)*(tblPrices[Product Code]="PSA"),tblPrices[Price]),0), 0 )} -> 507.53 | W37: dispatched | X37: paid,phone_call_required,fasting,online,ecg_uploaded,viewed_online | Z37: 10033314 | AA37: T35 | AB37: {=_xlfn.LET(_xlpm.pc, UPPER(TRIM(M37)), LEFT(_xlpm.pc, MIN(FIND({0,1,2,3,4,5,6,7,8,9}, _xlpm.pc&"0123456789"))-1))} -> SL | AC37: T35 | AD37: =VLOOKUP(AB37, postcode_table!A:B, 2, FALSE) -> Slough | AE37: =IFERROR(_xlfn.XLOOKUP(AC37, price_lookup_table!$C:$C, price_lookup_table!$B:$B), "") -> Corporate Flex
A38: ALV | B38: 45685 | C38: 45667 | D38: screening | E38: Booked | F38: Brynn | G38: Darrach | H38: 9 Village Place | I38: Suite 88 | M38: RH4 3NX | N38: bdarrach10@chronoengine.com | O38: male | P38: 35199 | Q38: =DATEDIF(P38,B38,"Y") -> 28 | R38: 6FFF4DAE | S38: 447912042116 | T38: Advanced Plus | V38: {=IFERROR( _xlfn.XLOOKUP(1, (tblPrices[Prefix]=$AC38)*(tblPrices[Product Code]=$T38), tblPrices[Price] ), 0 ) + IF(ISNUMBER(SEARCH("Mammogram",$U38)), IFERROR(_xlfn.XLOOKUP(1,(tblPrices[Prefix]=$AC38)*(tblPrices[Product Code]="Mammogram"),tblPrices[Price]),0), 0 ) + IF(ISNUMBER(SEARCH("PSA",$U38)), IFERROR(_xlfn.XLOOKUP(1,(tblPrices[Prefix]=$AC38)*(tblPrices[Product Code]="PSA"),tblPrices[Price]),0), 0 )} -> 0 | W38: dispatched | X38: viewed_online,paid,fasting,online,ecg_uploaded | Z38: 21764128 | AA38: T35 | AB38: {=_xlfn.LET(_xlpm.pc, UPPER(TRIM(M38)), LEFT(_xlpm.pc, MIN(FIND({0,1,2,3,4,5,6,7,8,9}, _xlpm.pc&"0123456789"))-1))} -> RH | AC38: T35 | AD38: =VLOOKUP(AB38, postcode_table!A:B, 2, FALSE) -> Redhill | AE38: =IFERROR(_xlfn.XLOOKUP(AC38, price_lookup_table!$C:$C, price_lookup_table!$B:$B), "") -> Corporate Flex
A39: BSE | B39: 45685 | C39: 45664 | D39: screening | E39: Booked | F39: Chelsey | G39: Brumhead | H39: 69066 Manufacturers Hill | I39: 17th Floor | M39: CO10 0QX | N39: cbrumhead11@yelp.com | O39: female | P39: 29739 | Q39: =DATEDIF(P39,B39,"Y") -> 43 | R39: 7F62DB78 | S39: 447940160976 | T39: Advanced | V39: {=IFERROR( _xlfn.XLOOKUP(1, (tblPrices[Prefix]=$AC39)*(tblPrices[Product Code]=$T39), tblPrices[Price] ), 0 ) + IF(ISNUMBER(SEARCH("Mammogram",$U39)), IFERROR(_xlfn.XLOOKUP(1,(tblPrices[Prefix]=$AC39)*(tblPrices[Product Code]="Mammogram"),tblPrices[Price]),0), 0 ) + IF(ISNUMBER(SEARCH("PSA",$U39)), IFERROR(_xlfn.XLOOKUP(1,(tblPrices[Prefix]=$AC39)*(tblPrices[Product Code]="PSA"),tblPrices[Price]),0), 0 )} -> 507.53 | W39: dispatched | X39: paid,fasting,online,viewed_online | Z39: 22006288 | AA39: T35 | AB39: {=_xlfn.LET(_xlpm.pc, UPPER(TRIM(M39)), LEFT(_xlpm.pc, MIN(FIND({0,1,2,3,4,5,6,7,8,9}, _xlpm.pc&"0123456789"))-1))} -> CO | AC39: T35 | AD39: =VLOOKUP(AB39, postcode_table!A:B, 2, FALSE) -> Colchester | AE39: =IFERROR(_xlfn.XLOOKUP(AC39, price_lookup_table!$C:$C, price_lookup_table!$B:$B), "") -> Corporate Flex
A40: ALB | B40: 45685 | C40: 45664 | D40: screening | E40: Booked | F40: Eduino | G40: Allcott | H40: 13 Redwing Court | I40: 15th Floor | M40: IV1 3YG | N40: eallcott12@amazon.de | O40: female | P40: 29883 | Q40: =DATEDIF(P40,B40,"Y") -> 43 | R40: 6414EEA3 | S40: 447790171844 | T40: Advanced | V40: {=IFERROR( _xlfn.XLOOKUP(1, (tblPrices[Prefix]=$AC40)*(tblPrices[Product Code]=$T40), tblPrices[Price] ), 0 ) + IF(ISNUMBER(SEARCH("Mammogram",$U40)), IFERROR(_xlfn.XLOOKUP(1,(tblPrices[Prefix]=$AC40)*(tblPrices[Product Code]="Mammogram"),tblPrices[Price]),0), 0 ) + IF(ISNUMBER(SEARCH("PSA",$U40)), IFERROR(_xlfn.XLOOKUP(1,(tblPrices[Prefix]=$AC40)*(tblPrices[Product Code]="PSA"),tblPrices[Price]),0), 0 )} -> 507.53 | W40: dispatched | X40: paid,fasting,online,viewed_online | Z40: 22006569 | AA40: T35 | AB40: {=_xlfn.LET(_xlpm.pc, UPPER(TRIM(M40)), LEFT(_xlpm.pc, MIN(FIND({0,1,2,3,4,5,6,7,8,9}, _xlpm.pc&"0123456789"))-1))} -> IV | AC40: T35 | AD40: =VLOOKUP(AB40, postcode_table!A:B, 2, FALSE) -> Inverness | AE40: =IFERROR(_xlfn.XLOOKUP(AC40, price_lookup_table!$C:$C, price_lookup_table!$B:$B), "") -> Corporate Flex
A41: ALX | B41: 45685 | C41: 45670 | D41: screening | E41: Booked | F41: Emile | G41: Dow | H41: 13 Esker Plaza | I41: 9th Floor | M41: LA3 3NR | N41: edow13@examiner.com | O41: female | P41: 27168 | Q41: =DATEDIF(P41,B41,"Y") -> 50 | R41: 4.146e+16 | S41: 447808760944 | T41: Advanced | V41: {=IFERROR( _xlfn.XLOOKUP(1, (tblPrices[Prefix]=$AC41)*(tblPrices[Product Code]=$T41), tblPrices[Price] ), 0 ) + IF(ISNUMBER(SEARCH("Mammogram",$U41)), IFERROR(_xlfn.XLOOKUP(1,(tblPrices[Prefix]=$AC41)*(tblPrices[Product Code]="Mammogram"),tblPrices[Price]),0), 0 ) + IF(ISNUMBER(SEARCH("PSA",$U41)), IFERROR(_xlfn.XLOOKUP(1,(tblPrices[Prefix]=$AC41)*(tblPrices[Product Code]="PSA"),tblPrices[Price]),0), 0 )} -> 507.53 | W41: dispatched | X41: rescheduled,paid,fasting,online,ecg_uploaded,viewed_online | Z41: 21965691 | AA41: T35 | AB41: {=_xlfn.LET(_xlpm.pc, UPPER(TRIM(M41)), LEFT(_xlpm.pc, MIN(FIND({0,1,2,3,4,5,6,7,8,9}, _xlpm.pc&"0123456789"))-1))} -> LA | AC41: T35 | AD41: =VLOOKUP(AB41, postcode_table!A:B, 2, FALSE) -> Lancaster | AE41: =IFERROR(_xlfn.XLOOKUP(AC41, price_lookup_table!$C:$C, price_lookup_table!$B:$B), "") -> Corporate Flex
A42: ALV | B42: 45685 | C42: 45663 | D42: screening | E42: Booked | F42: Margaux | G42: Daglish | H42: 658 Prentice Place | I42: Room 759 | M42: RG41 4AT | N42: mdaglish14@prnewswire.com | O42: female | P42: 31391 | Q42: =DATEDIF(P42,B42,"Y") -> 39 | R42: C4B843A6 | S42: 447912782896 | T42: Advanced Plus | V42: {=IFERROR( _xlfn.XLOOKUP(1, (tblPrices[Prefix]=$AC42)*(tblPrices[Product Code]=$T42), tblPrices[Price] ), 0 ) + IF(ISNUMBER(SEARCH("Mammogram",$U42)), IFERROR(_xlfn.XLOOKUP(1,(tblPrices[Prefix]=$AC42)*(tblPrices[Product Code]="Mammogram"),tblPrices[Price]),0), 0 ) + IF(ISNUMBER(SEARCH("PSA",$U42)), IFERROR(_xlfn.XLOOKUP(1,(tblPrices[Prefix]=$AC42)*(tblPrices[Product Code]="PSA"),tblPrices[Price]),0), 0 )} -> 0 | W42: dispatched | X42: paid,fasting,amber,online,ecg_uploaded,viewed_online | Z42: 20526578 | AA42: T35 | AB42: {=_xlfn.LET(_xlpm.pc, UPPER(TRIM(M42)), LEFT(_xlpm.pc, MIN(FIND({0,1,2,3,4,5,6,7,8,9}, _xlpm.pc&"0123456789"))-1))} -> RG | AC42: T35 | AD42: =VLOOKUP(AB42, postcode_table!A:B, 2, FALSE) -> Reading | AE42: =IFERROR(_xlfn.XLOOKUP(AC42, price_lookup_table!$C:$C, price_lookup_table!$B:$B), "") -> Corporate Flex
A43: PRI | B43: 45686 | C43: 45672 | D43: screening | E43: Booked | F43: Randy | G43: Tremlett | H43: 27898 Butterfield Lane | I43: PO Box 26710 | M43: B50 4HJ | N43: rtremlett15@gnu.org | O43: male | P43: 36400 | Q43: =DATEDIF(P43,B43,"Y") -> 25 | R43: 4BBABA95 | S43: 447792197676 | T43: Advanced Plus | V43: {=IFERROR( _xlfn.XLOOKUP(1, (tblPrices[Prefix]=$AC43)*(tblPrices[Product Code]=$T43), tblPrices[Price] ), 0 ) + IF(ISNUMBER(SEARCH("Mammogram",$U43)), IFERROR(_xlfn.XLOOKUP(1,(tblPrices[Prefix]=$AC43)*(tblPrices[Product Code]="Mammogram"),tblPrices[Price]),0), 0 ) + IF(ISNUMBER(SEARCH("PSA",$U43)), IFERROR(_xlfn.XLOOKUP(1,(tblPrices[Prefix]=$AC43)*(tblPrices[Product Code]="PSA"),tblPrices[Price]),0), 0 )} -> 0 | W43: dispatched | X43: viewed_online,paid,fasting,amber,online | Z43: 17520340 | AA43: T35 | AB43: {=_xlfn.LET(_xlpm.pc, UPPER(TRIM(M43)), LEFT(_xlpm.pc, MIN(FIND({0,1,2,3,4,5,6,7,8,9}, _xlpm.pc&"0123456789"))-1))} -> B | AC43: T35 | AD43: =VLOOKUP(AB43, postcode_table!A:B, 2, FALSE) -> Birmingham | AE43: =IFERROR(_xlfn.XLOOKUP(AC43, price_lookup_table!$C:$C, price_lookup_table!$B:$B), "") -> Corporate Flex
A44: ALV | B44: 45686 | C44: 45666 | D44: screening | E44: Booked | F44: Bernita | G44: Nickerson | H44: 014 Everett Court | I44: PO Box 9757 | M44: RG4 6SY | N44: bnickerson16@arstechnica.com | O44: male | P44: 22534 | Q44: =DATEDIF(P44,B44,"Y") -> 63 | R44: BCD2115E | S44: 447741638502 | T44: Advanced | V44: {=IFERROR( _xlfn.XLOOKUP(1, (tblPrices[Prefix]=$AC44)*(tblPrices[Product Code]=$T44), tblPrices[Price] ), 0 ) + IF(ISNUMBER(SEARCH("Mammogram",$U44)), IFERROR(_xlfn.XLOOKUP(1,(tblPrices[Prefix]=$AC44)*(tblPrices[Product Code]="Mammogram"),tblPrices[Price]),0), 0 ) + IF(ISNUMBER(SEARCH("PSA",$U44)), IFERROR(_xlfn.XLOOKUP(1,(tblPrices[Prefix]=$AC44)*(tblPrices[Product Code]="PSA"),tblPrices[Price]),0), 0 )} -> 507.53 | W44: dispatched | X44: paid,fasting,online,ecg_uploaded,viewed_online | Z44: 22010546 | AA44: T35 | AB44: {=_xlfn.LET(_xlpm.pc, UPPER(TRIM(M44)), LEFT(_xlpm.pc, MIN(FIND({0,1,2,3,4,5,6,7,8,9}, _xlpm.pc&"0123456789"))-1))} -> RG | AC44: T35 | AD44: =VLOOKUP(AB44, postcode_table!A:B, 2, FALSE) -> Reading | AE44: =IFERROR(_xlfn.XLOOKUP(AC44, price_lookup_table!$C:$C, price_lookup_table!$B:$B), "") -> Corporate Flex
A45: LIH | B45: 45686 | C45: 45677 | D45: screening | E45: Booked | F45: Carline | G45: Harly | H45: 1034 Stone Corner Lane | I45: Suite 95 | M45: SE1 8EH | N45: charly17@comsenz.com | O45: male | P45: 32171 | Q45: =DATEDIF(P45,B45,"Y") -> 37 | R45: C8BE9C4E | S45: 447977941613 | T45: Advanced Plus | V45: {=IFERROR( _xlfn.XLOOKUP(1, (tblPrices[Prefix]=$AC45)*(tblPrices[Product Code]=$T45), tblPrices[Price] ), 0 ) + IF(ISNUMBER(SEARCH("Mammogram",$U45)), IFERROR(_xlfn.XLOOKUP(1,(tblPrices[Prefix]=$AC45)*(tblPrices[Product Code]="Mammogram"),tblPrices[Price]),0), 0 ) + IF(ISNUMBER(SEARCH("PSA",$U45)), IFERROR(_xlfn.XLOOKUP(1,(tblPrices[Prefix]=$AC45)*(tblPrices[Product Code]="PSA"),tblPrices[Price]),0), 0 )} -> 0 | W45: dispatched | X45: paid,fasting,online,viewed_online | Z45: 21139819 | AA45: T35 | AB45: {=_xlfn.LET(_xlpm.pc, UPPER(TRIM(M45)), LEFT(_xlpm.pc, MIN(FIND({0,1,2,3,4,5,6,7,8,9}, _xlpm.pc&"0123456789"))-1))} -> SE | AC45: T35 | AD45: =VLOOKUP(AB45, postcode_table!A:B, 2, FALSE) -> South East London | AE45: =IFERROR(_xlfn.XLOOKUP(AC45, price_lookup_table!$C:$C, price_lookup_table!$B:$B), "") -> Corporate Flex
A46: SYC | B46: 45686 | C46: 45663 | D46: screening | E46: Booked | F46: Tybi | G46: Olczyk | H46: 836 Saint Paul Lane | I46: 1st Floor | M46: TW8 8EL | N46: tolczyk18@canalblog.com | O46: female | P46: 20315 | Q46: =DATEDIF(P46,B46,"Y") -> 69 | R46: 8EC497CD | S46: 447811167848 | T46: Advanced | U46: MAMMOGRAM | V46: {=IFERROR( _xlfn.XLOOKUP(1, (tblPrices[Prefix]=$AC46)*(tblPrices[Product Code]=$T46), tblPrices[Price] ), 0 ) + IF(ISNUMBER(SEARCH("Mammogram",$U46)), IFERROR(_xlfn.XLOOKUP(1,(tblPrices[Prefix]=$AC46)*(tblPrices[Product Code]="Mammogram"),tblPrices[Price]),0), 0 ) + IF(ISNUMBER(SEARCH("PSA",$U46)), IFERROR(_xlfn.XLOOKUP(1,(tblPrices[Prefix]=$AC46)*(tblPrices[Product Code]="PSA"),tblPrices[Price]),0), 0 )} -> 647.53 | W46: dispatched | X46: paid,fasting,online,viewed_online | Z46: 17498219 | AA46: T35 | AB46: {=_xlfn.LET(_xlpm.pc, UPPER(TRIM(M46)), LEFT(_xlpm.pc, MIN(FIND({0,1,2,3,4,5,6,7,8,9}, _xlpm.pc&"0123456789"))-1))} -> TW | AC46: T35 | AD46: =VLOOKUP(AB46, postcode_table!A:B, 2, FALSE) -> Twickenham | AE46: =IFERROR(_xlfn.XLOOKUP(AC46, price_lookup_table!$C:$C, price_lookup_table!$B:$B), "") -> Corporate Flex
A47: ALV | B47: 45686 | C47: 45677 | D47: screening | E47: Booked | F47: Garth | G47: Sails | H47: 41853 Golden Leaf Crossing | I47: Apt 1635 | M47: W2 2NQ | N47: gsails19@deviantart.com | O47: male | P47: 30788 | Q47: =DATEDIF(P47,B47,"Y") -> 40 | R47: BA464EAD | S47: 447812925745 | T47: Advanced | V47: {=IFERROR( _xlfn.XLOOKUP(1, (tblPrices[Prefix]=$AC47)*(tblPrices[Product Code]=$T47), tblPrices[Price] ), 0 ) + IF(ISNUMBER(SEARCH("Mammogram",$U47)), IFERROR(_xlfn.XLOOKUP(1,(tblPrices[Prefix]=$AC47)*(tblPrices[Product Code]="Mammogram"),tblPrices[Price]),0), 0 ) + IF(ISNUMBER(SEARCH("PSA",$U47)), IFERROR(_xlfn.XLOOKUP(1,(tblPrices[Prefix]=$AC47)*(tblPrices[Product Code]="PSA"),tblPrices[Price]),0), 0 )} -> 507.53 | W47: dispatched | X47: paid,fasting,online,ecg_uploaded,viewed_online | Z47: 17243728 | AA47: T35 | AB47: {=_xlfn.LET(_xlpm.pc, UPPER(TRIM(M47)), LEFT(_xlpm.pc, MIN(FIND({0,1,2,3,4,5,6,7,8,9}, _xlpm.pc&"0123456789"))-1))} -> W | AC47: T35 | AD47: =VLOOKUP(AB47, postcode_table!A:B, 2, FALSE) -> West London | AE47: =IFERROR(_xlfn.XLOOKUP(AC47, price_lookup_table!$C:$C, price_lookup_table!$B:$B), "") -> Corporate Flex
A48: RID | B48: 45687 | C48: 45677 | D48: screening | E48: Booked | F48: Hinda | G48: Bereford | H48: 75 Maywood Alley | I48: 3rd Floor | M48: BS31 2GE | N48: hbereford1a@army.mil | O48: male | P48: 34599 | Q48: =DATEDIF(P48,B48,"Y") -> 30 | R48: 7DB36EBC | S48: 447779101987 | T48: Advanced | V48: {=IFERROR( _xlfn.XLOOKUP(1, (tblPrices[Prefix]=$AC48)*(tblPrices[Product Code]=$T48), tblPrices[Price] ), 0 ) + IF(ISNUMBER(SEARCH("Mammogram",$U48)), IFERROR(_xlfn.XLOOKUP(1,(tblPrices[Prefix]=$AC48)*(tblPrices[Product Code]="Mammogram"),tblPrices[Price]),0), 0 ) + IF(ISNUMBER(SEARCH("PSA",$U48)), IFERROR(_xlfn.XLOOKUP(1,(tblPrices[Prefix]=$AC48)*(tblPrices[Product Code]="PSA"),tblPrices[Price]),0), 0 )} -> 507.53 | W48: dispatched | X48: paid,phone_call_required,fasting,online,viewed_online | Z48: 22022295 | AA48: T35 | AB48: {=_xlfn.LET(_xlpm.pc, UPPER(TRIM(M48)), LEFT(_xlpm.pc, MIN(FIND({0,1,2,3,4,5,6,7,8,9}, _xlpm.pc&"0123456789"))-1))} -> BS | AC48: T35 | AD48: =VLOOKUP(AB48, postcode_table!A:B, 2, FALSE) -> Bristol | AE48: =IFERROR(_xlfn.XLOOKUP(AC48, price_lookup_table!$C:$C, price_lookup_table!$B:$B), "") -> Corporate Flex
A49: MNR | B49: 45687 | C49: 45665 | D49: screening | E49: Booked | F49: Berkeley | G49: McAvin | H49: 157 Barnett Parkway | I49: Suite 89 | M49: SG19 2LP | N49: bmcavin1b@cdbaby.com | O49: male | P49: 24355 | Q49: =DATEDIF(P49,B49,"Y") -> 58 | R49: AA8BBFA8 | S49: 447803953767 | T49: Advanced | V49: {=IFERROR( _xlfn.XLOOKUP(1, (tblPrices[Prefix]=$AC49)*(tblPrices[Product Code]=$T49), tblPrices[Price] ), 0 ) + IF(ISNUMBER(SEARCH("Mammogram",$U49)), IFERROR(_xlfn.XLOOKUP(1,(tblPrices[Prefix]=$AC49)*(tblPrices[Product Code]="Mammogram"),tblPrices[Price]),0), 0 ) + IF(ISNUMBER(SEARCH("PSA",$U49)), IFERROR(_xlfn.XLOOKUP(1,(tblPrices[Prefix]=$AC49)*(tblPrices[Product Code]="PSA"),tblPrices[Price]),0), 0 )} -> 507.53 | W49: dispatched | X49: viewed_online,paid,fasting,online,ecg_uploaded | Z49: 19902318 | AA49: T35 | AB49: {=_xlfn.LET(_xlpm.pc, UPPER(TRIM(M49)), LEFT(_xlpm.pc, MIN(FIND({0,1,2,3,4,5,6,7,8,9}, _xlpm.pc&"0123456789"))-1))} -> SG | AC49: T35 | AD49: =VLOOKUP(AB49, postcode_table!A:B, 2, FALSE) -> Stevenage | AE49: =IFERROR(_xlfn.XLOOKUP(AC49, price_lookup_table!$C:$C, price_lookup_table!$B:$B), "") -> Corporate Flex
A50: RHB | B50: 45687 | C50: 45684 | D50: screening | E50: Booked | F50: Dre | G50: Gidley | H50: 85906 Iowa Road | I50: 16th Floor | M50: KA10 7NG | N50: dgidley1c@ucla.edu | O50: male | P50: 23813 | Q50: =DATEDIF(P50,B50,"Y") -> 59 | R50: F6A85FD5 | S50: 447732893813 | T50: Advanced Plus | V50: {=IFERROR( _xlfn.XLOOKUP(1, (tblPrices[Prefix]=$AC50)*(tblPrices[Product Code]=$T50), tblPrices[Price] ), 0 ) + IF(ISNUMBER(SEARCH("Mammogram",$U50)), IFERROR(_xlfn.XLOOKUP(1,(tblPrices[Prefix]=$AC50)*(tblPrices[Product Code]="Mammogram"),tblPrices[Price]),0), 0 ) + IF(ISNUMBER(SEARCH("PSA",$U50)), IFERROR(_xlfn.XLOOKUP(1,(tblPrices[Prefix]=$AC50)*(tblPrices[Product Code]="PSA"),tblPrices[Price]),0), 0 )} -> 0 | W50: dispatched | X50: paid,fasting,online,ecg_uploaded,viewed_online | Z50: 17798485 | AA50: T35 | AB50: {=_xlfn.LET(_xlpm.pc, UPPER(TRIM(M50)), LEFT(_xlpm.pc, MIN(FIND({0,1,2,3,4,5,6,7,8,9}, _xlpm.pc&"0123456789"))-1))} -> KA | AC50: T35 | AD50: =VLOOKUP(AB50, postcode_table!A:B, 2, FALSE) -> Kilmarnock | AE50: =IFERROR(_xlfn.XLOOKUP(AC50, price_lookup_table!$C:$C, price_lookup_table!$B:$B), "") -> Corporate Flex
A51: RHB | B51: 45687 | C51: 45671 | D51: screening | E51: Booked | F51: Albertina | G51: Vigars | H51: 031 Continental Terrace | I51: PO Box 19220 | M51: G66 5BS | N51: avigars1d@uol.com.br | O51: male | P51: 33087 | Q51: =DATEDIF(P51,B51,"Y") -> 34 | R51: F43A1D37 | S51: 447813181172 | T51: Advanced Plus | V51: {=IFERROR( _xlfn.XLOOKUP(1, (tblPrices[Prefix]=$AC51)*(tblPrices[Product Code]=$T51), tblPrices[Price] ), 0 ) + IF(ISNUMBER(SEARCH("Mammogram",$U51)), IFERROR(_xlfn.XLOOKUP(1,(tblPrices[Prefix]=$AC51)*(tblPrices[Product Code]="Mammogram"),tblPrices[Price]),0), 0 ) + IF(ISNUMBER(SEARCH("PSA",$U51)), IFERROR(_xlfn.XLOOKUP(1,(tblPrices[Prefix]=$AC51)*(tblPrices[Product Code]="PSA"),tblPrices[Price]),0), 0 )} -> 0 | W51: dispatched | X51: paid,phone_call_required,fasting,online,ecg_uploaded,viewed_online | Z51: 22015250 | AA51: T35 | AB51: {=_xlfn.LET(_xlpm.pc, UPPER(TRIM(M51)), LEFT(_xlpm.pc, MIN(FIND({0,1,2,3,4,5,6,7,8,9}, _xlpm.pc&"0123456789"))-1))} -> G | AC51: T35 | AD51: =VLOOKUP(AB51, postcode_table!A:B, 2, FALSE) -> Glasgow | AE51: =IFERROR(_xlfn.XLOOKUP(AC51, price_lookup_table!$C:$C, price_lookup_table!$B:$B), "") -> Corporate Flex
A52: ALV | B52: 45688 | C52: 45679 | D52: screening | E52: Booked | F52: Herbie | G52: Pund | H52: 981 Morning Point | I52: PO Box 66206 | M52: BN14 7EW | N52: hpund1e@about.me | O52: female | P52: 33657 | Q52: =DATEDIF(P52,B52,"Y") -> 32 | R52: 1B113C1B | S52: 447872925876 | T52: Advanced | V52: {=IFERROR( _xlfn.XLOOKUP(1, (tblPrices[Prefix]=$AC52)*(tblPrices[Product Code]=$T52), tblPrices[Price] ), 0 ) + IF(ISNUMBER(SEARCH("Mammogram",$U52)), IFERROR(_xlfn.XLOOKUP(1,(tblPrices[Prefix]=$AC52)*(tblPrices[Product Code]="Mammogram"),tblPrices[Price]),0), 0 ) + IF(ISNUMBER(SEARCH("PSA",$U52)), IFERROR(_xlfn.XLOOKUP(1,(tblPrices[Prefix]=$AC52)*(tblPrices[Product Code]="PSA"),tblPrices[Price]),0), 0 )} -> 507.53 | W52: dispatched | X52: paid,phone_call_required,fasting,online,ecg_uploaded,viewed_online | Z52: 22027005 | AA52: T35 | AB52: {=_xlfn.LET(_xlpm.pc, UPPER(TRIM(M52)), LEFT(_xlpm.pc, MIN(FIND({0,1,2,3,4,5,6,7,8,9}, _xlpm.pc&"0123456789"))-1))} -> BN | AC52: T35 | AD52: =VLOOKUP(AB52, postcode_table!A:B, 2, FALSE) -> Brighton | AE52: =IFERROR(_xlfn.XLOOKUP(AC52, price_lookup_table!$C:$C, price_lookup_table!$B:$B), "") -> Corporate Flex
A53: GAR | B53: 45688 | C53: 45667 | D53: screening | E53: Booked | F53: Gard | G53: Buzzing | H53: 9 Trailsway Way | I53: 1st Floor | M53: SG13 8BJ | N53: gbuzzing1f@harvard.edu | O53: male | P53: 14783 | Q53: =DATEDIF(P53,B53,"Y") -> 84 | R53: EFBAA221 | S53: 447818457514 | T53: Advanced | V53: {=IFERROR( _xlfn.XLOOKUP(1, (tblPrices[Prefix]=$AC53)*(tblPrices[Product Code]=$T53), tblPrices[Price] ), 0 ) + IF(ISNUMBER(SEARCH("Mammogram",$U53)), IFERROR(_xlfn.XLOOKUP(1,(tblPrices[Prefix]=$AC53)*(tblPrices[Product Code]="Mammogram"),tblPrices[Price]),0), 0 ) + IF(ISNUMBER(SEARCH("PSA",$U53)), IFERROR(_xlfn.XLOOKUP(1,(tblPrices[Prefix]=$AC53)*(tblPrices[Product Code]="PSA"),tblPrices[Price]),0), 0 )} -> 507.53 | W53: dispatched | X53: paid,fasting,amber,online,viewed_online | Z53: 21081340 | AA53: T35 | AB53: {=_xlfn.LET(_xlpm.pc, UPPER(TRIM(M53)), LEFT(_xlpm.pc, MIN(FIND({0,1,2,3,4,5,6,7,8,9}, _xlpm.pc&"0123456789"))-1))} -> SG | AC53: T35 | AD53: =VLOOKUP(AB53, postcode_table!A:B, 2, FALSE) -> Stevenage | AE53: =IFERROR(_xlfn.XLOOKUP(AC53, price_lookup_table!$C:$C, price_lookup_table!$B:$B), "") -> Corporate Flex
A54: BSE | B54: 45688 | C54: 45681 | D54: screening | E54: Booked | F54: Ephraim | G54: Larchier | H54: 62 Tony Place | I54: Suite 76 | M54: IP29 5LH | N54: elarchier1g@4shared.com | O54: male | P54: 25581 | Q54: =DATEDIF(P54,B54,"Y") -> 55 | R54: 5FC593A6 | S54: 447362202191 | T54: Essential | V54: {=IFERROR( _xlfn.XLOOKUP(1, (tblPrices[Prefix]=$AC54)*(tblPrices[Product Code]=$T54), tblPrices[Price] ), 0 ) + IF(ISNUMBER(SEARCH("Mammogram",$U54)), IFERROR(_xlfn.XLOOKUP(1,(tblPrices[Prefix]=$AC54)*(tblPrices[Product Code]="Mammogram"),tblPrices[Price]),0), 0 ) + IF(ISNUMBER(SEARCH("PSA",$U54)), IFERROR(_xlfn.XLOOKUP(1,(tblPrices[Prefix]=$AC54)*(tblPrices[Product Code]="PSA"),tblPrices[Price]),0), 0 )} -> 0 | W54: dispatched | X54: paid,fasting,online,viewed_online | Z54: 22030700 | AA54: T35 | AB54: {=_xlfn.LET(_xlpm.pc, UPPER(TRIM(M54)), LEFT(_xlpm.pc, MIN(FIND({0,1,2,3,4,5,6,7,8,9}, _xlpm.pc&"0123456789"))-1))} -> IP | AC54: T35 | AD54: =VLOOKUP(AB54, postcode_table!A:B, 2, FALSE) -> Ipswich | AE54: =IFERROR(_xlfn.XLOOKUP(AC54, price_lookup_table!$C:$C, price_lookup_table!$B:$B), "") -> Corporate Flex
A55: ALV | B55: 45691 | C55: 45687 | D55: screening | E55: Booked | F55: Thatch | G55: Casbon | H55: 83 Ridgeview Junction | I55: PO Box 96685 | M55: GU22 7EE | N55: tcasbon1h@unesco.org | O55: male | P55: 22329 | Q55: =DATEDIF(P55,B55,"Y") -> 63 | R55: AA510A5E | S55: 447785387795 | T55: Advanced Plus | V55: {=IFERROR( _xlfn.XLOOKUP(1, (tblPrices[Prefix]=$AC55)*(tblPrices[Product Code]=$T55), tblPrices[Price] ), 0 ) + IF(ISNUMBER(SEARCH("Mammogram",$U55)), IFERROR(_xlfn.XLOOKUP(1,(tblPrices[Prefix]=$AC55)*(tblPrices[Product Code]="Mammogram"),tblPrices[Price]),0), 0 ) + IF(ISNUMBER(SEARCH("PSA",$U55)), IFERROR(_xlfn.XLOOKUP(1,(tblPrices[Prefix]=$AC55)*(tblPrices[Product Code]="PSA"),tblPrices[Price]),0), 0 )} -> 0 | W55: dispatched | X55: paid,fasting,amber,online,ecg_uploaded,viewed_online | Z55: 17193620 | AA55: T35 | AB55: {=_xlfn.LET(_xlpm.pc, UPPER(TRIM(M55)), LEFT(_xlpm.pc, MIN(FIND({0,1,2,3,4,5,6,7,8,9}, _xlpm.pc&"0123456789"))-1))} -> GU | AC55: T35 | AD55: =VLOOKUP(AB55, postcode_table!A:B, 2, FALSE) -> Guildford | AE55: =IFERROR(_xlfn.XLOOKUP(AC55, price_lookup_table!$C:$C, price_lookup_table!$B:$B), "") -> Corporate Flex
A56: LIH | B56: 45691 | C56: 45685 | D56: screening | E56: Booked | F56: Kaylil | G56: Allberry | H56: 20386 Fairview Crossing | I56: PO Box 19206 | M56: N5 1PL | N56: kallberry1i@hugedomains.com | O56: male | P56: 31061 | Q56: =DATEDIF(P56,B56,"Y") -> 40 | R56: 459CB3AB | S56: 447940253204 | T56: Advanced | V56: {=IFERROR( _xlfn.XLOOKUP(1, (tblPrices[Prefix]=$AC56)*(tblPrices[Product Code]=$T56), tblPrices[Price] ), 0 ) + IF(ISNUMBER(SEARCH("Mammogram",$U56)), IFERROR(_xlfn.XLOOKUP(1,(tblPrices[Prefix]=$AC56)*(tblPrices[Product Code]="Mammogram"),tblPrices[Price]),0), 0 ) + IF(ISNUMBER(SEARCH("PSA",$U56)), IFERROR(_xlfn.XLOOKUP(1,(tblPrices[Prefix]=$AC56)*(tblPrices[Product Code]="PSA"),tblPrices[Price]),0), 0 )} -> 507.53 | W56: dispatched | X56: rescheduled,viewed_online,paid,fasting,online | Z56: 12016809 | AA56: T35 | AB56: {=_xlfn.LET(_xlpm.pc, UPPER(TRIM(M56)), LEFT(_xlpm.pc, MIN(FIND({0,1,2,3,4,5,6,7,8,9}, _xlpm.pc&"0123456789"))-1))} -> N | AC56: T35 | AD56: =VLOOKUP(AB56, postcode_table!A:B, 2, FALSE) -> North London | AE56: =IFERROR(_xlfn.XLOOKUP(AC56, price_lookup_table!$C:$C, price_lookup_table!$B:$B), "") -> Corporate Flex
A57: LIH | B57: 45691 | C57: 45684 | D57: screening | E57: Booked | F57: Dorelle | G57: Tort | H57: 12 Express Drive | I57: Apt 1633 | M57: SE4 1RD | N57: dtort1j@feedburner.com | O57: female | P57: 28688 | Q57: =DATEDIF(P57,B57,"Y") -> 46 | R57: CE7A87C9 | S57: 447850076594 | T57: Advanced | V57: {=IFERROR( _xlfn.XLOOKUP(1, (tblPrices[Prefix]=$AC57)*(tblPrices[Product Code]=$T57), tblPrices[Price] ), 0 ) + IF(ISNUMBER(SEARCH("Mammogram",$U57)), IFERROR(_xlfn.XLOOKUP(1,(tblPrices[Prefix]=$AC57)*(tblPrices[Product Code]="Mammogram"),tblPrices[Price]),0), 0 ) + IF(ISNUMBER(SEARCH("PSA",$U57)), IFERROR(_xlfn.XLOOKUP(1,(tblPrices[Prefix]=$AC57)*(tblPrices[Product Code]="PSA"),tblPrices[Price]),0), 0 )} -> 507.53 | W57: dispatched | X57: viewed_online,paid,fasting,online | Z57: 22032733 | AA57: T35 | AB57: {=_xlfn.LET(_xlpm.pc, UPPER(TRIM(M57)), LEFT(_xlpm.pc, MIN(FIND({0,1,2,3,4,5,6,7,8,9}, _xlpm.pc&"0123456789"))-1))} -> SE | AC57: T35 | AD57: =VLOOKUP(AB57, postcode_table!A:B, 2, FALSE) -> South East London | AE57: =IFERROR(_xlfn.XLOOKUP(AC57, price_lookup_table!$C:$C, price_lookup_table!$B:$B), "") -> Corporate Flex
A58: SLO | B58: 45691 | C58: 45663 | D58: screening | E58: Booked | F58: Thurstan | G58: cornhill | H58: 4484 Carey Place | I58: PO Box 24122 | M58: SW17 7DW | N58: tcornhill1k@sitemeter.com | O58: male | P58: 25462 | Q58: =DATEDIF(P58,B58,"Y") -> 55 | R58: 3E00691F | S58: 447785512955 | T58: Advanced | V58: {=IFERROR( _xlfn.XLOOKUP(1, (tblPrices[Prefix]=$AC58)*(tblPrices[Product Code]=$T58), tblPrices[Price] ), 0 ) + IF(ISNUMBER(SEARCH("Mammogram",$U58)), IFERROR(_xlfn.XLOOKUP(1,(tblPrices[Prefix]=$AC58)*(tblPrices[Product Code]="Mammogram"),tblPrices[Price]),0), 0 ) + IF(ISNUMBER(SEARCH("PSA",$U58)), IFERROR(_xlfn.XLOOKUP(1,(tblPrices[Prefix]=$AC58)*(tblPrices[Product Code]="PSA"),tblPrices[Price]),0), 0 )} -> 507.53 | W58: dispatched | X58: viewed_online,paid,fasting,online | Z58: 17202107 | AA58: T35 | AB58: {=_xlfn.LET(_xlpm.pc, UPPER(TRIM(M58)), LEFT(_xlpm.pc, MIN(FIND({0,1,2,3,4,5,6,7,8,9}, _xlpm.pc&"0123456789"))-1))} -> SW | AC58: T35 | AD58: =VLOOKUP(AB58, postcode_table!A:B, 2, FALSE) -> South West London | AE58: =IFERROR(_xlfn.XLOOKUP(AC58, price_lookup_table!$C:$C, price_lookup_table!$B:$B), "") -> Corporate Flex
... A60: PRI | B60: 45691 | C60: 45680 | D60: screening | E60: Booked | F60: Sapphira | G60: Swanton | H60: 03685 Schiller Trail | I60: PO Box 18349 | M60: B92 8BU | N60: sswanton1m@cmu.edu | O60: female | P60: 27597 | Q60: =DATEDIF(P60,B60,"Y") -> 49 | R60: 8EAEFB28 | S60: 447917792601 | T60: Advanced Plus | V60: {=IFERROR( _xlfn.XLOOKUP(1, (tblPrices[Prefix]=$AC60)*(tblPrices[Product Code]=$T60), tblPrices[Price] ), 0 ) + IF(ISNUMBER(SEARCH("Mammogram",$U60)), IFERROR(_xlfn.XLOOKUP(1,(tblPrices[Prefix]=$AC60)*(tblPrices[Product Code]="Mammogram"),tblPrices[Price]),0), 0 ) + IF(ISNUMBER(SEARCH("PSA",$U60)), IFERROR(_xlfn.XLOOKUP(1,(tblPrices[Prefix]=$AC60)*(tblPrices[Product Code]="PSA"),tblPrices[Price]),0), 0 )} -> 0 | W60: dispatched | X60: viewed_online,paid,fasting,online | Z60: 19257564 | AA60: T35 | AB60: {=_xlfn.LET(_xlpm.pc, UPPER(TRIM(M60)), LEFT(_xlpm.pc, MIN(FIND({0,1,2,3,4,5,6,7,8,9}, _xlpm.pc&"0123456789"))-1))} -> B | AC60: T35 | AD60: =VLOOKUP(AB60, postcode_table!A:B, 2, FALSE) -> Birmingham | AE60: =IFERROR(_xlfn.XLOOKUP(AC60, price_lookup_table!$C:$C, price_lookup_table!$B:$B), "") -> Corporate Flex
A61: ALV | B61: 45691 | C61: 45665 | D61: screening | E61: Booked | F61: Ringo | G61: Poundford | H61: 09 Thompson Street | I61: Suite 33 | M61: BA10 0PQ | N61: rpoundford1n@mac.com | O61: male | P61: 25912 | Q61: =DATEDIF(P61,B61,"Y") -> 54 | R61: F1B4315C | S61: 447939536351 | T61: Advanced Plus | V61: {=IFERROR( _xlfn.XLOOKUP(1, (tblPrices[Prefix]=$AC61)*(tblPrices[Product Code]=$T61), tblPrices[Price] ), 0 ) + IF(ISNUMBER(SEARCH("Mammogram",$U61)), IFERROR(_xlfn.XLOOKUP(1,(tblPrices[Prefix]=$AC61)*(tblPrices[Product Code]="Mammogram"),tblPrices[Price]),0), 0 ) + IF(ISNUMBER(SEARCH("PSA",$U61)), IFERROR(_xlfn.XLOOKUP(1,(tblPrices[Prefix]=$AC61)*(tblPrices[Product Code]="PSA"),tblPrices[Price]),0), 0 )} -> 970.5 | W61: dispatched | X61: rescheduled,paid,fasting,amber,online,ecg_uploaded,viewed_online | Z61: 21962046 | AA61: M01Phone | AB61: {=_xlfn.LET(_xlpm.pc, UPPER(TRIM(M61)), LEFT(_xlpm.pc, MIN(FIND({0,1,2,3,4,5,6,7,8,9}, _xlpm.pc&"0123456789"))-1))} -> BA | AC61: =LEFT(AA61, 3) -> M01 | AD61: =VLOOKUP(AB61, postcode_table!A:B, 2, FALSE) -> Bath | AE61: =IFERROR(_xlfn.XLOOKUP(AC61, price_lookup_table!$C:$C, price_lookup_table!$B:$B), "") -> Self Pay
A62: THO | B62: 45691 | C62: 45666 | D62: screening | E62: Booked | F62: George | G62: Allum | H62: 8 Fulton Lane | I62: PO Box 13866 | M62: HD9 3FA | N62: gallum1o@seattletimes.com | O62: male | P62: 36013 | Q62: =DATEDIF(P62,B62,"Y") -> 26 | R62: 83EC217B | T62: Advanced Plus | V62: {=IFERROR( _xlfn.XLOOKUP(1, (tblPrices[Prefix]=$AC62)*(tblPrices[Product Code]=$T62), tblPrices[Price] ), 0 ) + IF(ISNUMBER(SEARCH("Mammogram",$U62)), IFERROR(_xlfn.XLOOKUP(1,(tblPrices[Prefix]=$AC62)*(tblPrices[Product Code]="Mammogram"),tblPrices[Price]),0), 0 ) + IF(ISNUMBER(SEARCH("PSA",$U62)), IFERROR(_xlfn.XLOOKUP(1,(tblPrices[Prefix]=$AC62)*(tblPrices[Product Code]="PSA"),tblPrices[Price]),0), 0 )} -> 970.5 | W62: dispatched | X62: paid,fasting,green,online,viewed_online | Z62: 16419057 | AA62: M01Phone | AB62: {=_xlfn.LET(_xlpm.pc, UPPER(TRIM(M62)), LEFT(_xlpm.pc, MIN(FIND({0,1,2,3,4,5,6,7,8,9}, _xlpm.pc&"0123456789"))-1))} -> HD | AC62: =LEFT(AA62, 3) -> M01 | AD62: =VLOOKUP(AB62, postcode_table!A:B, 2, FALSE) -> Huddersfield | AE62: =IFERROR(_xlfn.XLOOKUP(AC62, price_lookup_table!$C:$C, price_lookup_table!$B:$B), "") -> Self Pay
A63: ALB | B63: 45692 | C63: 45678 | D63: screening | E63: Booked | F63: Dodie | G63: Coulling | H63: 2882 Wayridge Avenue | I63: PO Box 36240 | M63: AB15 9LQ | N63: dcoulling1p@usa.gov | O63: male | P63: 28156 | Q63: =DATEDIF(P63,B63,"Y") -> 48 | R63: 99B953F3 | S63: 447770414997 | T63: Advanced | V63: {=IFERROR( _xlfn.XLOOKUP(1, (tblPrices[Prefix]=$AC63)*(tblPrices[Product Code]=$T63), tblPrices[Price] ), 0 ) + IF(ISNUMBER(SEARCH("Mammogram",$U63)), IFERROR(_xlfn.XLOOKUP(1,(tblPrices[Prefix]=$AC63)*(tblPrices[Product Code]="Mammogram"),tblPrices[Price]),0), 0 ) + IF(ISNUMBER(SEARCH("PSA",$U63)), IFERROR(_xlfn.XLOOKUP(1,(tblPrices[Prefix]=$AC63)*(tblPrices[Product Code]="PSA"),tblPrices[Price]),0), 0 )} -> 543 | W63: dispatched | X63: paid,fasting,online,viewed_online | Z63: 15453719 | AA63: AXAMEMBER | AB63: {=_xlfn.LET(_xlpm.pc, UPPER(TRIM(M63)), LEFT(_xlpm.pc, MIN(FIND({0,1,2,3,4,5,6,7,8,9}, _xlpm.pc&"0123456789"))-1))} -> AB | AC63: =LEFT(AA63, 3) -> AXA | AD63: =VLOOKUP(AB63, postcode_table!A:B, 2, FALSE) -> Aberdeen | AE63: =IFERROR(_xlfn.XLOOKUP(AC63, price_lookup_table!$C:$C, price_lookup_table!$B:$B), "") -> Self Pay
A64: ALB | B64: 45692 | C64: 45678 | D64: screening | E64: Booked | F64: Parnell | G64: Hillyatt | H64: 0552 Summerview Street | I64: 4th Floor | M64: AB15 9LQ | N64: phillyatt1q@exblog.jp | O64: female | P64: 20447 | Q64: =DATEDIF(P64,B64,"Y") -> 69 | R64: 2C20E681 | S64: 447762175832 | T64: Advanced | V64: {=IFERROR( _xlfn.XLOOKUP(1, (tblPrices[Prefix]=$AC64)*(tblPrices[Product Code]=$T64), tblPrices[Price] ), 0 ) + IF(ISNUMBER(SEARCH("Mammogram",$U64)), IFERROR(_xlfn.XLOOKUP(1,(tblPrices[Prefix]=$AC64)*(tblPrices[Product Code]="Mammogram"),tblPrices[Price]),0), 0 ) + IF(ISNUMBER(SEARCH("PSA",$U64)), IFERROR(_xlfn.XLOOKUP(1,(tblPrices[Prefix]=$AC64)*(tblPrices[Product Code]="PSA"),tblPrices[Price]),0), 0 )} -> 543 | W64: dispatched | X64: paid,fasting,online,viewed_online | Z64: 19567994 | AA64: AXAMEMBEROFFER | AB64: {=_xlfn.LET(_xlpm.pc, UPPER(TRIM(M64)), LEFT(_xlpm.pc, MIN(FIND({0,1,2,3,4,5,6,7,8,9}, _xlpm.pc&"0123456789"))-1))} -> AB | AC64: =LEFT(AA64, 3) -> AXA | AD64: =VLOOKUP(AB64, postcode_table!A:B, 2, FALSE) -> Aberdeen | AE64: =IFERROR(_xlfn.XLOOKUP(AC64, price_lookup_table!$C:$C, price_lookup_table!$B:$B), "") -> Self Pay
A65: ALV | B65: 45692 | C65: 45674 | D65: screening | E65: Booked | F65: Hugh | G65: Bulmer | H65: 62 Eastwood Junction | I65: Apt 1796 | M65: KT24 5RJ | N65: hbulmer1r@google.cn | O65: female | P65: 20972 | Q65: =DATEDIF(P65,B65,"Y") -> 67 | R65: 7AEC2251 | S65: 447508042487 | T65: Advanced Plus | V65: {=IFERROR( _xlfn.XLOOKUP(1, (tblPrices[Prefix]=$AC65)*(tblPrices[Product Code]=$T65), tblPrices[Price] ), 0 ) + IF(ISNUMBER(SEARCH("Mammogram",$U65)), IFERROR(_xlfn.XLOOKUP(1,(tblPrices[Prefix]=$AC65)*(tblPrices[Product Code]="Mammogram"),tblPrices[Price]),0), 0 ) + IF(ISNUMBER(SEARCH("PSA",$U65)), IFERROR(_xlfn.XLOOKUP(1,(tblPrices[Prefix]=$AC65)*(tblPrices[Product Code]="PSA"),tblPrices[Price]),0), 0 )} -> 728 | W65: dispatched | X65: paid,fasting,amber,online,ecg_uploaded,viewed_online | Z65: 22020490 | AA65: AXAMEMBER | AB65: {=_xlfn.LET(_xlpm.pc, UPPER(TRIM(M65)), LEFT(_xlpm.pc, MIN(FIND({0,1,2,3,4,5,6,7,8,9}, _xlpm.pc&"0123456789"))-1))} -> KT | AC65: =LEFT(AA65, 3) -> AXA | AD65: =VLOOKUP(AB65, postcode_table!A:B, 2, FALSE) -> Kingston upon Thames | AE65: =IFERROR(_xlfn.XLOOKUP(AC65, price_lookup_table!$C:$C, price_lookup_table!$B:$B), "") -> Self Pay
A66: ALV | B66: 45692 | C66: 45667 | D66: screening | E66: Booked | F66: Sigvard | G66: Steuhlmeyer | H66: 6 Anniversary Point | I66: Room 487 | M66: RH13 6RG | N66: ssteuhlmeyer1s@gnu.org | O66: male | P66: 17306 | Q66: =DATEDIF(P66,B66,"Y") -> 77 | R66: 27AB8ED8 | S66: 447881903049 | T66: Advanced Plus | V66: {=IFERROR( _xlfn.XLOOKUP(1, (tblPrices[Prefix]=$AC66)*(tblPrices[Product Code]=$T66), tblPrices[Price] ), 0 ) + IF(ISNUMBER(SEARCH("Mammogram",$U66)), IFERROR(_xlfn.XLOOKUP(1,(tblPrices[Prefix]=$AC66)*(tblPrices[Product Code]="Mammogram"),tblPrices[Price]),0), 0 ) + IF(ISNUMBER(SEARCH("PSA",$U66)), IFERROR(_xlfn.XLOOKUP(1,(tblPrices[Prefix]=$AC66)*(tblPrices[Product Code]="PSA"),tblPrices[Price]),0), 0 )} -> 728 | W66: dispatched | X66: paid,fasting,online,ecg_uploaded,viewed_online | Z66: 22011647 | AA66: AXAMEMBER | AB66: {=_xlfn.LET(_xlpm.pc, UPPER(TRIM(M66)), LEFT(_xlpm.pc, MIN(FIND({0,1,2,3,4,5,6,7,8,9}, _xlpm.pc&"0123456789"))-1))} -> RH | AC66: =LEFT(AA66, 3) -> AXA | AD66: =VLOOKUP(AB66, postcode_table!A:B, 2, FALSE) -> Redhill | AE66: =IFERROR(_xlfn.XLOOKUP(AC66, price_lookup_table!$C:$C, price_lookup_table!$B:$B), "") -> Self Pay
A67: BTH | B67: 45692 | C67: 45663 | D67: screening | E67: Booked | F67: Hewitt | G67: Drydale | H67: 1425 Butterfield Alley | I67: Suite 51 | M67: BA2 6BD | N67: hdrydale1t@amazonaws.com | O67: female | P67: 26897 | Q67: =DATEDIF(P67,B67,"Y") -> 51 | R67: 73ED65A8 | S67: 447899790448 | T67: Advanced | V67: {=IFERROR( _xlfn.XLOOKUP(1, (tblPrices[Prefix]=$AC67)*(tblPrices[Product Code]=$T67), tblPrices[Price] ), 0 ) + IF(ISNUMBER(SEARCH("Mammogram",$U67)), IFERROR(_xlfn.XLOOKUP(1,(tblPrices[Prefix]=$AC67)*(tblPrices[Product Code]="Mammogram"),tblPrices[Price]),0), 0 ) + IF(ISNUMBER(SEARCH("PSA",$U67)), IFERROR(_xlfn.XLOOKUP(1,(tblPrices[Prefix]=$AC67)*(tblPrices[Product Code]="PSA"),tblPrices[Price]),0), 0 )} -> 724.5 | W67: dispatched | X67: paid,fasting,online,ecg_uploaded,viewed_online | Z67: 13035206 | AA67: M01Phone | AB67: {=_xlfn.LET(_xlpm.pc, UPPER(TRIM(M67)), LEFT(_xlpm.pc, MIN(FIND({0,1,2,3,4,5,6,7,8,9}, _xlpm.pc&"0123456789"))-1))} -> BA | AC67: =LEFT(AA67, 3) -> M01 | AD67: =VLOOKUP(AB67, postcode_table!A:B, 2, FALSE) -> Bath | AE67: =IFERROR(_xlfn.XLOOKUP(AC67, price_lookup_table!$C:$C, price_lookup_table!$B:$B), "") -> Self Pay
A68: ALV | B68: 45692 | C68: 45666 | D68: screening | E68: Booked | F68: Odele | G68: Ogilvie | H68: 63 Tony Road | I68: Apt 1628 | M68: KT11 2HY | N68: oogilvie1u@comcast.net | O68: male | P68: 33037 | Q68: =DATEDIF(P68,B68,"Y") -> 34 | R68: 67A50D23 | S68: 447973655648 | T68: Advanced Plus | V68: {=IFERROR( _xlfn.XLOOKUP(1, (tblPrices[Prefix]=$AC68)*(tblPrices[Product Code]=$T68), tblPrices[Price] ), 0 ) + IF(ISNUMBER(SEARCH("Mammogram",$U68)), IFERROR(_xlfn.XLOOKUP(1,(tblPrices[Prefix]=$AC68)*(tblPrices[Product Code]="Mammogram"),tblPrices[Price]),0), 0 ) + IF(ISNUMBER(SEARCH("PSA",$U68)), IFERROR(_xlfn.XLOOKUP(1,(tblPrices[Prefix]=$AC68)*(tblPrices[Product Code]="PSA"),tblPrices[Price]),0), 0 )} -> 970.5 | W68: dispatched | X68: rescheduled,paid,fasting,green,online,ecg_uploaded,viewed_online | Z68: 17094828 | AA68: M01Phone | AB68: {=_xlfn.LET(_xlpm.pc, UPPER(TRIM(M68)), LEFT(_xlpm.pc, MIN(FIND({0,1,2,3,4,5,6,7,8,9}, _xlpm.pc&"0123456789"))-1))} -> KT | AC68: =LEFT(AA68, 3) -> M01 | AD68: =VLOOKUP(AB68, postcode_table!A:B, 2, FALSE) -> Kingston upon Thames | AE68: =IFERROR(_xlfn.XLOOKUP(AC68, price_lookup_table!$C:$C, price_lookup_table!$B:$B), "") -> Self Pay
A69: BTH | B69: 45693 | C69: 45684 | D69: screening | E69: Booked | F69: Brittany | G69: Axworthy | H69: 4246 Bayside Lane | I69: Apt 1459 | M69: SN13 8DY | N69: baxworthy1v@hp.com | O69: male | P69: 15947 | Q69: =DATEDIF(P69,B69,"Y") -> 81 | R69: F958141F | S69: 447887950229 | T69: Select | V69: {=IFERROR( _xlfn.XLOOKUP(1, (tblPrices[Prefix]=$AC69)*(tblPrices[Product Code]=$T69), tblPrices[Price] ), 0 ) + IF(ISNUMBER(SEARCH("Mammogram",$U69)), IFERROR(_xlfn.XLOOKUP(1,(tblPrices[Prefix]=$AC69)*(tblPrices[Product Code]="Mammogram"),tblPrices[Price]),0), 0 ) + IF(ISNUMBER(SEARCH("PSA",$U69)), IFERROR(_xlfn.XLOOKUP(1,(tblPrices[Prefix]=$AC69)*(tblPrices[Product Code]="PSA"),tblPrices[Price]),0), 0 )} -> 357 | W69: dispatched | X69: paid,fasting,online,ecg_uploaded,viewed_online | Z69: 13007616 | AA69: AXAMEMBEROFFERPAZXSX32ZD | AB69: {=_xlfn.LET(_xlpm.pc, UPPER(TRIM(M69)), LEFT(_xlpm.pc, MIN(FIND({0,1,2,3,4,5,6,7,8,9}, _xlpm.pc&"0123456789"))-1))} -> SN | AC69: =LEFT(AA69, 3) -> AXA | AD69: =VLOOKUP(AB69, postcode_table!A:B, 2, FALSE) -> Swindon | AE69: =IFERROR(_xlfn.XLOOKUP(AC69, price_lookup_table!$C:$C, price_lookup_table!$B:$B), "") -> Self Pay
A70: ALV | B70: 45693 | C70: 45671 | D70: screening | E70: Booked | F70: Mattheus | G70: Savins | H70: 8421 Mcbride Road | I70: Room 636 | M70: KT23 4HL | N70: msavins1w@zimbio.com | O70: female | P70: 30887 | Q70: =DATEDIF(P70,B70,"Y") -> 40 | R70: DAD3ED74 | S70: 447912212381 | T70: Advanced | V70: {=IFERROR( _xlfn.XLOOKUP(1, (tblPrices[Prefix]=$AC70)*(tblPrices[Product Code]=$T70), tblPrices[Price] ), 0 ) + IF(ISNUMBER(SEARCH("Mammogram",$U70)), IFERROR(_xlfn.XLOOKUP(1,(tblPrices[Prefix]=$AC70)*(tblPrices[Product Code]="Mammogram"),tblPrices[Price]),0), 0 ) + IF(ISNUMBER(SEARCH("PSA",$U70)), IFERROR(_xlfn.XLOOKUP(1,(tblPrices[Prefix]=$AC70)*(tblPrices[Product Code]="PSA"),tblPrices[Price]),0), 0 )} -> 724.5 | W70: dispatched | X70: paid,fasting,online,ecg_uploaded,viewed_online | Z70: 22015830 | AA70: M01Phone | AB70: {=_xlfn.LET(_xlpm.pc, UPPER(TRIM(M70)), LEFT(_xlpm.pc, MIN(FIND({0,1,2,3,4,5,6,7,8,9}, _xlpm.pc&"0123456789"))-1))} -> KT | AC70: =LEFT(AA70, 3) -> M01 | AD70: =VLOOKUP(AB70, postcode_table!A:B, 2, FALSE) -> Kingston upon Thames | AE70: =IFERROR(_xlfn.XLOOKUP(AC70, price_lookup_table!$C:$C, price_lookup_table!$B:$B), "") -> Self Pay
A71: CHI | B71: 45693 | C71: 45659 | D71: screening | E71: Booked | F71: Stanly | G71: Abrahmson | H71: 5 Buhler Plaza | I71: 3rd Floor | M71: OX33 1JT | N71: sabrahmson1x@jiathis.com | O71: male | P71: 29848 | Q71: =DATEDIF(P71,B71,"Y") -> 43 | R71: 324CA53D | S71: 447817204760 | T71: Advanced | V71: {=IFERROR( _xlfn.XLOOKUP(1, (tblPrices[Prefix]=$AC71)*(tblPrices[Product Code]=$T71), tblPrices[Price] ), 0 ) + IF(ISNUMBER(SEARCH("Mammogram",$U71)), IFERROR(_xlfn.XLOOKUP(1,(tblPrices[Prefix]=$AC71)*(tblPrices[Product Code]="Mammogram"),tblPrices[Price]),0), 0 ) + IF(ISNUMBER(SEARCH("PSA",$U71)), IFERROR(_xlfn.XLOOKUP(1,(tblPrices[Prefix]=$AC71)*(tblPrices[Product Code]="PSA"),tblPrices[Price]),0), 0 )} -> 724.5 | W71: dispatched | X71: paid,fasting,online,ecg_uploaded,viewed_online | Z71: 10931841 | AA71: M01Phone | AB71: {=_xlfn.LET(_xlpm.pc, UPPER(TRIM(M71)), LEFT(_xlpm.pc, MIN(FIND({0,1,2,3,4,5,6,7,8,9}, _xlpm.pc&"0123456789"))-1))} -> OX | AC71: =LEFT(AA71, 3) -> M01 | AD71: =VLOOKUP(AB71, postcode_table!A:B, 2, FALSE) -> Oxford | AE71: =IFERROR(_xlfn.XLOOKUP(AC71, price_lookup_table!$C:$C, price_lookup_table!$B:$B), "") -> Self Pay
A72: CHI | B72: 45693 | C72: 45659 | D72: screening | E72: Booked | F72: Giffer | G72: Houdmont | H72: 696 Myrtle Park | I72: Suite 68 | M72: OX33 1JT | N72: ghoudmont1y@ustream.tv | O72: female | P72: 33879 | Q72: =DATEDIF(P72,B72,"Y") -> 32 | R72: 7338A6D4 | S72: 447836625999 | T72: Advanced | V72: {=IFERROR( _xlfn.XLOOKUP(1, (tblPrices[Prefix]=$AC72)*(tblPrices[Product Code]=$T72), tblPrices[Price] ), 0 ) + IF(ISNUMBER(SEARCH("Mammogram",$U72)), IFERROR(_xlfn.XLOOKUP(1,(tblPrices[Prefix]=$AC72)*(tblPrices[Product Code]="Mammogram"),tblPrices[Price]),0), 0 ) + IF(ISNUMBER(SEARCH("PSA",$U72)), IFERROR(_xlfn.XLOOKUP(1,(tblPrices[Prefix]=$AC72)*(tblPrices[Product Code]="PSA"),tblPrices[Price]),0), 0 )} -> 724.5 | W72: dispatched | X72: paid,fasting,online,ecg_uploaded,viewed_online | Z72: 14655034 | AA72: M01Phone | AB72: {=_xlfn.LET(_xlpm.pc, UPPER(TRIM(M72)), LEFT(_xlpm.pc, MIN(FIND({0,1,2,3,4,5,6,7,8,9}, _xlpm.pc&"0123456789"))-1))} -> OX | AC72: =LEFT(AA72, 3) -> M01 | AD72: =VLOOKUP(AB72, postcode_table!A:B, 2, FALSE) -> Oxford | AE72: =IFERROR(_xlfn.XLOOKUP(AC72, price_lookup_table!$C:$C, price_lookup_table!$B:$B), "") -> Self Pay
A73: ALB | B73: 45694 | C73: 45665 | D73: screening | E73: Booked | F73: Myrtle | G73: Remirez | H73: 605 Leroy Avenue | I73: Room 979 | M73: AB16 7HT | N73: mremirez1z@fotki.com | O73: male | P73: 28627 | Q73: =DATEDIF(P73,B73,"Y") -> 46 | R73: 4B9A73B2 | S73: 447805082888 | T73: Select | V73: {=IFERROR( _xlfn.XLOOKUP(1, (tblPrices[Prefix]=$AC73)*(tblPrices[Product Code]=$T73), tblPrices[Price] ), 0 ) + IF(ISNUMBER(SEARCH("Mammogram",$U73)), IFERROR(_xlfn.XLOOKUP(1,(tblPrices[Prefix]=$AC73)*(tblPrices[Product Code]="Mammogram"),tblPrices[Price]),0), 0 ) + IF(ISNUMBER(SEARCH("PSA",$U73)), IFERROR(_xlfn.XLOOKUP(1,(tblPrices[Prefix]=$AC73)*(tblPrices[Product Code]="PSA"),tblPrices[Price]),0), 0 )} -> 357 | W73: dispatched | X73: paid,fasting,online,viewed_online | Z73: 22008557 | AA73: AXAMEMBER | AB73: {=_xlfn.LET(_xlpm.pc, UPPER(TRIM(M73)), LEFT(_xlpm.pc, MIN(FIND({0,1,2,3,4,5,6,7,8,9}, _xlpm.pc&"0123456789"))-1))} -> AB | AC73: =LEFT(AA73, 3) -> AXA | AD73: =VLOOKUP(AB73, postcode_table!A:B, 2, FALSE) -> Aberdeen | AE73: =IFERROR(_xlfn.XLOOKUP(AC73, price_lookup_table!$C:$C, price_lookup_table!$B:$B), "") -> Self Pay
A74: SRD | B74: 45694 | C74: 45674 | D74: screening | E74: Booked | F74: Johnny | G74: Tomaello | H74: 0649 1st Point | I74: 14th Floor | M74: BH7 6PE | N74: jtomaello20@chicagotribune.com | O74: male | P74: 15261 | Q74: =DATEDIF(P74,B74,"Y") -> 83 | R74: 734645AE | S74: +44 7711835481 | T74: Advanced | V74: {=IFERROR( _xlfn.XLOOKUP(1, (tblPrices[Prefix]=$AC74)*(tblPrices[Product Code]=$T74), tblPrices[Price] ), 0 ) + IF(ISNUMBER(SEARCH("Mammogram",$U74)), IFERROR(_xlfn.XLOOKUP(1,(tblPrices[Prefix]=$AC74)*(tblPrices[Product Code]="Mammogram"),tblPrices[Price]),0), 0 ) + IF(ISNUMBER(SEARCH("PSA",$U74)), IFERROR(_xlfn.XLOOKUP(1,(tblPrices[Prefix]=$AC74)*(tblPrices[Product Code]="PSA"),tblPrices[Price]),0), 0 )} -> 543 | W74: dispatched | X74: paid,fasting,red,online,ecg_uploaded,viewed_online | Z74: 21450091 | AA74: AXAMEMBEROFFER | AB74: {=_xlfn.LET(_xlpm.pc, UPPER(TRIM(M74)), LEFT(_xlpm.pc, MIN(FIND({0,1,2,3,4,5,6,7,8,9}, _xlpm.pc&"0123456789"))-1))} -> BH | AC74: =LEFT(AA74, 3) -> AXA | AD74: =VLOOKUP(AB74, postcode_table!A:B, 2, FALSE) -> Bournemouth | AE74: =IFERROR(_xlfn.XLOOKUP(AC74, price_lookup_table!$C:$C, price_lookup_table!$B:$B), "") -> Self Pay
A75: SRD | B75: 45694 | C75: 45673 | D75: screening | E75: Booked | F75: Gottfried | G75: Montilla | H75: 20615 Hoffman Crossing | I75: Room 642 | M75: SO45 4BX | N75: gmontilla21@canalblog.com | O75: female | P75: 17274 | Q75: =DATEDIF(P75,B75,"Y") -> 77 | R75: 30D28005 | S75: 447813139473 | T75: Advanced | V75: {=IFERROR( _xlfn.XLOOKUP(1, (tblPrices[Prefix]=$AC75)*(tblPrices[Product Code]=$T75), tblPrices[Price] ), 0 ) + IF(ISNUMBER(SEARCH("Mammogram",$U75)), IFERROR(_xlfn.XLOOKUP(1,(tblPrices[Prefix]=$AC75)*(tblPrices[Product Code]="Mammogram"),tblPrices[Price]),0), 0 ) + IF(ISNUMBER(SEARCH("PSA",$U75)), IFERROR(_xlfn.XLOOKUP(1,(tblPrices[Prefix]=$AC75)*(tblPrices[Product Code]="PSA"),tblPrices[Price]),0), 0 )} -> 543 | W75: dispatched | X75: rescheduled,paid,fasting,amber,online,ecg_uploaded,viewed_online | Z75: 22019971 | AA75: AXAMEMBER | AB75: {=_xlfn.LET(_xlpm.pc, UPPER(TRIM(M75)), LEFT(_xlpm.pc, MIN(FIND({0,1,2,3,4,5,6,7,8,9}, _xlpm.pc&"0123456789"))-1))} -> SO | AC75: =LEFT(AA75, 3) -> AXA | AD75: =VLOOKUP(AB75, postcode_table!A:B, 2, FALSE) -> Southampton | AE75: =IFERROR(_xlfn.XLOOKUP(AC75, price_lookup_table!$C:$C, price_lookup_table!$B:$B), "") -> Self Pay
A76: LIH | B76: 45694 | C76: 45693 | D76: screening | E76: Booked | F76: Kellyann | G76: Sebborn | H76: 7853 Bluestem Crossing | I76: Room 783 | M76: WC1N 3PJ | N76: ksebborn22@ycombinator.com | O76: male | P76: 31491 | Q76: =DATEDIF(P76,B76,"Y") -> 38 | R76: D7673C98 | S76: 447365598114 | T76: Essential | V76: {=IFERROR( _xlfn.XLOOKUP(1, (tblPrices[Prefix]=$AC76)*(tblPrices[Product Code]=$T76), tblPrices[Price] ), 0 ) + IF(ISNUMBER(SEARCH("Mammogram",$U76)), IFERROR(_xlfn.XLOOKUP(1,(tblPrices[Prefix]=$AC76)*(tblPrices[Product Code]="Mammogram"),tblPrices[Price]),0), 0 ) + IF(ISNUMBER(SEARCH("PSA",$U76)), IFERROR(_xlfn.XLOOKUP(1,(tblPrices[Prefix]=$AC76)*(tblPrices[Product Code]="PSA"),tblPrices[Price]),0), 0 )} -> 185 | W76: dispatched | X76: paid,fasting,online | Z76: 22044695 | AA76: AXAMEMBEROFFERC9HGXXUY3K | AB76: {=_xlfn.LET(_xlpm.pc, UPPER(TRIM(M76)), LEFT(_xlpm.pc, MIN(FIND({0,1,2,3,4,5,6,7,8,9}, _xlpm.pc&"0123456789"))-1))} -> WC | AC76: =LEFT(AA76, 3) -> AXA | AD76: =VLOOKUP(AB76, postcode_table!A:B, 2, FALSE) -> West Central London | AE76: =IFERROR(_xlfn.XLOOKUP(AC76, price_lookup_table!$C:$C, price_lookup_table!$B:$B), "") -> Self Pay
A77: ALB | B77: 45694 | C77: 45678 | D77: screening | E77: Booked | F77: Sandye | G77: Wordley | H77: 6 Grim Street | I77: 19th Floor | M77: AB30 1EW | N77: swordley23@seesaa.net | O77: male | P77: 30497 | Q77: =DATEDIF(P77,B77,"Y") -> 41 | R77: 421C2195 | S77: 447507068811 | T77: Advanced | V77: {=IFERROR( _xlfn.XLOOKUP(1, (tblPrices[Prefix]=$AC77)*(tblPrices[Product Code]=$T77), tblPrices[Price] ), 0 ) + IF(ISNUMBER(SEARCH("Mammogram",$U77)), IFERROR(_xlfn.XLOOKUP(1,(tblPrices[Prefix]=$AC77)*(tblPrices[Product Code]="Mammogram"),tblPrices[Price]),0), 0 ) + IF(ISNUMBER(SEARCH("PSA",$U77)), IFERROR(_xlfn.XLOOKUP(1,(tblPrices[Prefix]=$AC77)*(tblPrices[Product Code]="PSA"),tblPrices[Price]),0), 0 )} -> 724.5 | W77: dispatched | X77: viewed_online,paid,fasting,online | Z77: 13774573 | AA77: M01Phone | AB77: {=_xlfn.LET(_xlpm.pc, UPPER(TRIM(M77)), LEFT(_xlpm.pc, MIN(FIND({0,1,2,3,4,5,6,7,8,9}, _xlpm.pc&"0123456789"))-1))} -> AB | AC77: =LEFT(AA77, 3) -> M01 | AD77: =VLOOKUP(AB77, postcode_table!A:B, 2, FALSE) -> Aberdeen | AE77: =IFERROR(_xlfn.XLOOKUP(AC77, price_lookup_table!$C:$C, price_lookup_table!$B:$B), "") -> Self Pay
A78: ALB | B78: 45694 | C78: 45679 | D78: screening | E78: Booked | F78: Ira | G78: Petrolli | H78: 40 Wayridge Trail | I78: PO Box 67302 | M78: AB31 5UE | N78: ipetrolli24@printfriendly.com | O78: female | P78: 29375 | Q78: =DATEDIF(P78,B78,"Y") -> 44 | R78: 6EBA8321 | S78: 447748208020 | T78: Advanced | V78: {=IFERROR( _xlfn.XLOOKUP(1, (tblPrices[Prefix]=$AC78)*(tblPrices[Product Code]=$T78), tblPrices[Price] ), 0 ) + IF(ISNUMBER(SEARCH("Mammogram",$U78)), IFERROR(_xlfn.XLOOKUP(1,(tblPrices[Prefix]=$AC78)*(tblPrices[Product Code]="Mammogram"),tblPrices[Price]),0), 0 ) + IF(ISNUMBER(SEARCH("PSA",$U78)), IFERROR(_xlfn.XLOOKUP(1,(tblPrices[Prefix]=$AC78)*(tblPrices[Product Code]="PSA"),tblPrices[Price]),0), 0 )} -> 724.5 | W78: dispatched | X78: paid,fasting,online,viewed_online | Z78: 22025737 | AA78: M01Phone | AB78: {=_xlfn.LET(_xlpm.pc, UPPER(TRIM(M78)), LEFT(_xlpm.pc, MIN(FIND({0,1,2,3,4,5,6,7,8,9}, _xlpm.pc&"0123456789"))-1))} -> AB | AC78: =LEFT(AA78, 3) -> M01 | AD78: =VLOOKUP(AB78, postcode_table!A:B, 2, FALSE) -> Aberdeen | AE78: =IFERROR(_xlfn.XLOOKUP(AC78, price_lookup_table!$C:$C, price_lookup_table!$B:$B), "") -> Self Pay
A79: CHI | B79: 45694 | C79: 45666 | D79: screening | E79: Booked | F79: Nancy | G79: Padmore | H79: 09926 West Terrace | I79: 6th Floor | M79: HP7 0LW | N79: npadmore25@symantec.com | O79: female | P79: 23468 | Q79: =DATEDIF(P79,B79,"Y") -> 60 | R79: D343E783 | S79: 441494726263 | T79: Advanced | V79: {=IFERROR( _xlfn.XLOOKUP(1, (tblPrices[Prefix]=$AC79)*(tblPrices[Product Code]=$T79), tblPrices[Price] ), 0 ) + IF(ISNUMBER(SEARCH("Mammogram",$U79)), IFERROR(_xlfn.XLOOKUP(1,(tblPrices[Prefix]=$AC79)*(tblPrices[Product Code]="Mammogram"),tblPrices[Price]),0), 0 ) + IF(ISNUMBER(SEARCH("PSA",$U79)), IFERROR(_xlfn.XLOOKUP(1,(tblPrices[Prefix]=$AC79)*(tblPrices[Product Code]="PSA"),tblPrices[Price]),0), 0 )} -> 724.5 | W79: dispatched | X79: paid,phone_call_required,fasting,red,online,ecg_uploaded,viewed_online | Z79: 22010853 | AA79: M01phone | AB79: {=_xlfn.LET(_xlpm.pc, UPPER(TRIM(M79)), LEFT(_xlpm.pc, MIN(FIND({0,1,2,3,4,5,6,7,8,9}, _xlpm.pc&"0123456789"))-1))} -> HP | AC79: =LEFT(AA79, 3) -> M01 | AD79: =VLOOKUP(AB79, postcode_table!A:B, 2, FALSE) -> Hemel Hempstead | AE79: =IFERROR(_xlfn.XLOOKUP(AC79, price_lookup_table!$C:$C, price_lookup_table!$B:$B), "") -> Self Pay
A80: RHB | B80: 45694 | C80: 45688 | D80: screening | E80: Booked | F80: Scarlet | G80: Dines | H80: 75 High Crossing Center | I80: Room 1409 | M80: PA13 4NU | N80: sdines26@howstuffworks.com | O80: male | P80: 20983 | Q80: =DATEDIF(P80,B80,"Y") -> 67 | R80: D5280F62 | S80: 441505872057 | T80: Select | U80: PSA | V80: {=IFERROR( _xlfn.XLOOKUP(1, (tblPrices[Prefix]=$AC80)*(tblPrices[Product Code]=$T80), tblPrices[Price] ), 0 ) + IF(ISNUMBER(SEARCH("Mammogram",$U80)), IFERROR(_xlfn.XLOOKUP(1,(tblPrices[Prefix]=$AC80)*(tblPrices[Product Code]="Mammogram"),tblPrices[Price]),0), 0 ) + IF(ISNUMBER(SEARCH("PSA",$U80)), IFERROR(_xlfn.XLOOKUP(1,(tblPrices[Prefix]=$AC80)*(tblPrices[Product Code]="PSA"),tblPrices[Price]),0), 0 )} -> 588.5 | W80: dispatched | X80: rescheduled,paid,fasting,online,ecg_uploaded,viewed_online | Z80: 10479964 | AA80: M01phone | AB80: {=_xlfn.LET(_xlpm.pc, UPPER(TRIM(M80)), LEFT(_xlpm.pc, MIN(FIND({0,1,2,3,4,5,6,7,8,9}, _xlpm.pc&"0123456789"))-1))} -> PA | AC80: =LEFT(AA80, 3) -> M01 | AD80: =VLOOKUP(AB80, postcode_table!A:B, 2, FALSE) -> Paisley | AE80: =IFERROR(_xlfn.XLOOKUP(AC80, price_lookup_table!$C:$C, price_lookup_table!$B:$B), "") -> Self Pay
A81: RID | B81: 45694 | C81: 45659 | D81: screening | E81: Booked | F81: Vitia | G81: Dain | H81: 6249 Golf Road | I81: 9th Floor | M81: SN2 7QU | N81: vdain27@tmall.com | O81: male | P81: 29455 | Q81: =DATEDIF(P81,B81,"Y") -> 44 | R81: 9FE43FD4 | S81: 447717824765 | T81: Select | V81: {=IFERROR( _xlfn.XLOOKUP(1, (tblPrices[Prefix]=$AC81)*(tblPrices[Product Code]=$T81), tblPrices[Price] ), 0 ) + IF(ISNUMBER(SEARCH("Mammogram",$U81)), IFERROR(_xlfn.XLOOKUP(1,(tblPrices[Prefix]=$AC81)*(tblPrices[Product Code]="Mammogram"),tblPrices[Price]),0), 0 ) + IF(ISNUMBER(SEARCH("PSA",$U81)), IFERROR(_xlfn.XLOOKUP(1,(tblPrices[Prefix]=$AC81)*(tblPrices[Product Code]="PSA"),tblPrices[Price]),0), 0 )} -> 476.5 | W81: dispatched | X81: paid,fasting,online,viewed_online | Z81: 14044847 | AA81: M01Phone | AB81: {=_xlfn.LET(_xlpm.pc, UPPER(TRIM(M81)), LEFT(_xlpm.pc, MIN(FIND({0,1,2,3,4,5,6,7,8,9}, _xlpm.pc&"0123456789"))-1))} -> SN | AC81: =LEFT(AA81, 3) -> M01 | AD81: =VLOOKUP(AB81, postcode_table!A:B, 2, FALSE) -> Swindon | AE81: =IFERROR(_xlfn.XLOOKUP(AC81, price_lookup_table!$C:$C, price_lookup_table!$B:$B), "") -> Self Pay
A82: SRD | B82: 45694 | C82: 45686 | D82: screening | E82: Booked | F82: Audre | G82: Pittendreigh | H82: 24 Declaration Plaza | I82: Suite 3 | M82: SO16 4JD | N82: apittendreigh28@google.pl | O82: male | P82: 25805 | Q82: =DATEDIF(P82,B82,"Y") -> 54 | R82: D16B5535 | S82: 447785103655 | T82: Advanced | V82: {=IFERROR( _xlfn.XLOOKUP(1, (tblPrices[Prefix]=$AC82)*(tblPrices[Product Code]=$T82), tblPrices[Price] ), 0 ) + IF(ISNUMBER(SEARCH("Mammogram",$U82)), IFERROR(_xlfn.XLOOKUP(1,(tblPrices[Prefix]=$AC82)*(tblPrices[Product Code]="Mammogram"),tblPrices[Price]),0), 0 ) + IF(ISNUMBER(SEARCH("PSA",$U82)), IFERROR(_xlfn.XLOOKUP(1,(tblPrices[Prefix]=$AC82)*(tblPrices[Product Code]="PSA"),tblPrices[Price]),0), 0 )} -> 724.5 | W82: dispatched | X82: paid,fasting,amber,online,ecg_uploaded,viewed_online | Z82: 22036178 | AA82: M01Phone | AB82: {=_xlfn.LET(_xlpm.pc, UPPER(TRIM(M82)), LEFT(_xlpm.pc, MIN(FIND({0,1,2,3,4,5,6,7,8,9}, _xlpm.pc&"0123456789"))-1))} -> SO | AC82: =LEFT(AA82, 3) -> M01 | AD82: =VLOOKUP(AB82, postcode_table!A:B, 2, FALSE) -> Southampton | AE82: =IFERROR(_xlfn.XLOOKUP(AC82, price_lookup_table!$C:$C, price_lookup_table!$B:$B), "") -> Self Pay
A83: GAR | B83: 45695 | C83: 45680 | D83: screening | E83: Booked | F83: Stephen | G83: Croisdall | H83: 8 Nancy Park | I83: Suite 91 | M83: WD23 3DS | N83: scroisdall29@slashdot.org | O83: male | P83: 33280 | Q83: =DATEDIF(P83,B83,"Y") -> 33 | R83: 16137DC1 | S83: 447766077344 | T83: Advanced | V83: {=IFERROR( _xlfn.XLOOKUP(1, (tblPrices[Prefix]=$AC83)*(tblPrices[Product Code]=$T83), tblPrices[Price] ), 0 ) + IF(ISNUMBER(SEARCH("Mammogram",$U83)), IFERROR(_xlfn.XLOOKUP(1,(tblPrices[Prefix]=$AC83)*(tblPrices[Product Code]="Mammogram"),tblPrices[Price]),0), 0 ) + IF(ISNUMBER(SEARCH("PSA",$U83)), IFERROR(_xlfn.XLOOKUP(1,(tblPrices[Prefix]=$AC83)*(tblPrices[Product Code]="PSA"),tblPrices[Price]),0), 0 )} -> 543 | W83: dispatched | X83: paid,fasting,amber,online,viewed_online | Z83: 22029315 | AA83: AXAMEMBEROFFERURSFW8K9S4 | AB83: {=_xlfn.LET(_xlpm.pc, UPPER(TRIM(M83)), LEFT(_xlpm.pc, MIN(FIND({0,1,2,3,4,5,6,7,8,9}, _xlpm.pc&"0123456789"))-1))} -> WD | AC83: =LEFT(AA83, 3) -> AXA | AD83: =VLOOKUP(AB83, postcode_table!A:B, 2, FALSE) -> Watford | AE83: =IFERROR(_xlfn.XLOOKUP(AC83, price_lookup_table!$C:$C, price_lookup_table!$B:$B), "") -> Self Pay
A84: BSE | B84: 45695 | C84: 45692 | D84: screening | E84: Booked | F84: Duffy | G84: Spikings | H84: 3231 Jenifer Place | I84: 7th Floor | M84: IP30 0DT | N84: dspikings2a@google.pl | O84: male | P84: 19881 | Q84: =DATEDIF(P84,B84,"Y") -> 70 | R84: 9D91445B | S84: 447710782340 | T84: Essential | V84: {=IFERROR( _xlfn.XLOOKUP(1, (tblPrices[Prefix]=$AC84)*(tblPrices[Product Code]=$T84), tblPrices[Price] ), 0 ) + IF(ISNUMBER(SEARCH("Mammogram",$U84)), IFERROR(_xlfn.XLOOKUP(1,(tblPrices[Prefix]=$AC84)*(tblPrices[Product Code]="Mammogram"),tblPrices[Price]),0), 0 ) + IF(ISNUMBER(SEARCH("PSA",$U84)), IFERROR(_xlfn.XLOOKUP(1,(tblPrices[Prefix]=$AC84)*(tblPrices[Product Code]="PSA"),tblPrices[Price]),0), 0 )} -> 246 | W84: dispatched | X84: paid,fasting,viewed_online | Z84: 18555795 | AA84: M01Phone | AB84: {=_xlfn.LET(_xlpm.pc, UPPER(TRIM(M84)), LEFT(_xlpm.pc, MIN(FIND({0,1,2,3,4,5,6,7,8,9}, _xlpm.pc&"0123456789"))-1))} -> IP | AC84: =LEFT(AA84, 3) -> M01 | AD84: =VLOOKUP(AB84, postcode_table!A:B, 2, FALSE) -> Ipswich | AE84: =IFERROR(_xlfn.XLOOKUP(AC84, price_lookup_table!$C:$C, price_lookup_table!$B:$B), "") -> Self Pay
A85: LIN | B85: 45695 | C85: 45679 | D85: screening | E85: Booked | F85: Alisa | G85: Mew | H85: 7 Fieldstone Point | I85: Suite 59 | M85: LE14 4DD | N85: amew2b@delicious.com | O85: male | P85: 24709 | Q85: =DATEDIF(P85,B85,"Y") -> 57 | R85: C02A832F | S85: 447976510006 | T85: Advanced | V85: {=IFERROR( _xlfn.XLOOKUP(1, (tblPrices[Prefix]=$AC85)*(tblPrices[Product Code]=$T85), tblPrices[Price] ), 0 ) + IF(ISNUMBER(SEARCH("Mammogram",$U85)), IFERROR(_xlfn.XLOOKUP(1,(tblPrices[Prefix]=$AC85)*(tblPrices[Product Code]="Mammogram"),tblPrices[Price]),0), 0 ) + IF(ISNUMBER(SEARCH("PSA",$U85)), IFERROR(_xlfn.XLOOKUP(1,(tblPrices[Prefix]=$AC85)*(tblPrices[Product Code]="PSA"),tblPrices[Price]),0), 0 )} -> 543 | W85: dispatched | X85: paid,phone_call_required,fasting,red,online,viewed_online | Z85: 19071125 | AA85: T57 | AB85: {=_xlfn.LET(_xlpm.pc, UPPER(TRIM(M85)), LEFT(_xlpm.pc, MIN(FIND({0,1,2,3,4,5,6,7,8,9}, _xlpm.pc&"0123456789"))-1))} -> LE | AC85: axa | AD85: =VLOOKUP(AB85, postcode_table!A:B, 2, FALSE) -> Leicester | AE85: =IFERROR(_xlfn.XLOOKUP(AC85, price_lookup_table!$C:$C, price_lookup_table!$B:$B), "") -> Self Pay
A86: ALV | B86: 45698 | C86: 45693 | D86: screening | E86: Booked | F86: Harmonie | G86: Corkan | H86: 7345 Mosinee Plaza | I86: Suite 32 | M86: CT5 4AH | N86: hcorkan2c@wired.com | O86: male | P86: 22026 | Q86: =DATEDIF(P86,B86,"Y") -> 64 | R86: D926FF09 | S86: 447743841359 | T86: Advanced Plus | V86: {=IFERROR( _xlfn.XLOOKUP(1, (tblPrices[Prefix]=$AC86)*(tblPrices[Product Code]=$T86), tblPrices[Price] ), 0 ) + IF(ISNUMBER(SEARCH("Mammogram",$U86)), IFERROR(_xlfn.XLOOKUP(1,(tblPrices[Prefix]=$AC86)*(tblPrices[Product Code]="Mammogram"),tblPrices[Price]),0), 0 ) + IF(ISNUMBER(SEARCH("PSA",$U86)), IFERROR(_xlfn.XLOOKUP(1,(tblPrices[Prefix]=$AC86)*(tblPrices[Product Code]="PSA"),tblPrices[Price]),0), 0 )} -> 728 | W86: dispatched | X86: paid,phone_call_required,fasting,online,ecg_uploaded,viewed_online | Z86: 22044274 | AA86: AXAMEMBEROFFERLKKADKVE87 | AB86: {=_xlfn.LET(_xlpm.pc, UPPER(TRIM(M86)), LEFT(_xlpm.pc, MIN(FIND({0,1,2,3,4,5,6,7,8,9}, _xlpm.pc&"0123456789"))-1))} -> CT | AC86: =LEFT(AA86, 3) -> AXA | AD86: =VLOOKUP(AB86, postcode_table!A:B, 2, FALSE) -> Canterbury | AE86: =IFERROR(_xlfn.XLOOKUP(AC86, price_lookup_table!$C:$C, price_lookup_table!$B:$B), "") -> Self Pay
A87: SYC | B87: 45698 | C87: 45674 | D87: screening | E87: Booked | F87: Amalie | G87: Clymo | H87: 24 Bowman Terrace | I87: Apt 857 | M87: KT10 9LU | N87: aclymo2d@woothemes.com | O87: female | P87: 20248 | Q87: =DATEDIF(P87,B87,"Y") -> 69 | R87: AAA9554D | S87: 447495746204 | T87: Advanced | V87: {=IFERROR( _xlfn.XLOOKUP(1, (tblPrices[Prefix]=$AC87)*(tblPrices[Product Code]=$T87), tblPrices[Price] ), 0 ) + IF(ISNUMBER(SEARCH("Mammogram",$U87)), IFERROR(_xlfn.XLOOKUP(1,(tblPrices[Prefix]=$AC87)*(tblPrices[Product Code]="Mammogram"),tblPrices[Price]),0), 0 ) + IF(ISNUMBER(SEARCH("PSA",$U87)), IFERROR(_xlfn.XLOOKUP(1,(tblPrices[Prefix]=$AC87)*(tblPrices[Product Code]="PSA"),tblPrices[Price]),0), 0 )} -> 543 | W87: dispatched | X87: paid,fasting,viewed_online | Z87: 20855416 | AA87: AXAMEMBEROFFER | AB87: {=_xlfn.LET(_xlpm.pc, UPPER(TRIM(M87)), LEFT(_xlpm.pc, MIN(FIND({0,1,2,3,4,5,6,7,8,9}, _xlpm.pc&"0123456789"))-1))} -> KT | AC87: =LEFT(AA87, 3) -> AXA | AD87: =VLOOKUP(AB87, postcode_table!A:B, 2, FALSE) -> Kingston upon Thames | AE87: =IFERROR(_xlfn.XLOOKUP(AC87, price_lookup_table!$C:$C, price_lookup_table!$B:$B), "") -> Self Pay
A88: MNR | B88: 45698 | C88: 45671 | D88: screening | E88: Booked | F88: Banky | G88: Jorioz | H88: 7860 Miller Hill | I88: PO Box 57048 | M88: MK11 1DW | N88: bjorioz2e@sakura.ne.jp | O88: female | P88: 27583 | Q88: =DATEDIF(P88,B88,"Y") -> 49 | R88: 83E8A563 | S88: 447725984753 | T88: Advanced | V88: {=IFERROR( _xlfn.XLOOKUP(1, (tblPrices[Prefix]=$AC88)*(tblPrices[Product Code]=$T88), tblPrices[Price] ), 0 ) + IF(ISNUMBER(SEARCH("Mammogram",$U88)), IFERROR(_xlfn.XLOOKUP(1,(tblPrices[Prefix]=$AC88)*(tblPrices[Product Code]="Mammogram"),tblPrices[Price]),0), 0 ) + IF(ISNUMBER(SEARCH("PSA",$U88)), IFERROR(_xlfn.XLOOKUP(1,(tblPrices[Prefix]=$AC88)*(tblPrices[Product Code]="PSA"),tblPrices[Price]),0), 0 )} -> 543 | W88: dispatched | X88: viewed_online,paid,fasting,amber,online,ecg_uploaded | Z88: 19088078 | AA88: AXAMEMBER | AB88: {=_xlfn.LET(_xlpm.pc, UPPER(TRIM(M88)), LEFT(_xlpm.pc, MIN(FIND({0,1,2,3,4,5,6,7,8,9}, _xlpm.pc&"0123456789"))-1))} -> MK | AC88: =LEFT(AA88, 3) -> AXA | AD88: =VLOOKUP(AB88, postcode_table!A:B, 2, FALSE) -> Milton Keynes | AE88: =IFERROR(_xlfn.XLOOKUP(AC88, price_lookup_table!$C:$C, price_lookup_table!$B:$B), "") -> Self Pay
A89: PRK | B89: 45698 | C89: 45691 | D89: screening | E89: Booked | F89: Elfrieda | G89: Bramont | H89: 6 Vahlen Trail | I89: Apt 821 | M89: NG15 9HD | N89: ebramont2f@about.com | O89: male | P89: 17383 | Q89: =DATEDIF(P89,B89,"Y") -> 77 | R89: 0428289D | S89: 447989346080 | T89: Advanced Plus | V89: {=IFERROR( _xlfn.XLOOKUP(1, (tblPrices[Prefix]=$AC89)*(tblPrices[Product Code]=$T89), tblPrices[Price] ), 0 ) + IF(ISNUMBER(SEARCH("Mammogram",$U89)), IFERROR(_xlfn.XLOOKUP(1,(tblPrices[Prefix]=$AC89)*(tblPrices[Product Code]="Mammogram"),tblPrices[Price]),0), 0 ) + IF(ISNUMBER(SEARCH("PSA",$U89)), IFERROR(_xlfn.XLOOKUP(1,(tblPrices[Prefix]=$AC89)*(tblPrices[Product Code]="PSA"),tblPrices[Price]),0), 0 )} -> 728 | W89: dispatched | X89: rescheduled,viewed_online,paid,fasting,online,ecg_uploaded | Z89: 14503993 | AA89: AXAMEMBEROFFER | AB89: {=_xlfn.LET(_xlpm.pc, UPPER(TRIM(M89)), LEFT(_xlpm.pc, MIN(FIND({0,1,2,3,4,5,6,7,8,9}, _xlpm.pc&"0123456789"))-1))} -> NG | AC89: =LEFT(AA89, 3) -> AXA | AD89: =VLOOKUP(AB89, postcode_table!A:B, 2, FALSE) -> Nottingham | AE89: =IFERROR(_xlfn.XLOOKUP(AC89, price_lookup_table!$C:$C, price_lookup_table!$B:$B), "") -> Self Pay
A90: ALV | B90: 45698 | C90: 45680 | D90: screening | E90: Booked | F90: Guntar | G90: Scaice | H90: 290 Pine View Way | I90: Room 1490 | M90: RG30 4DP | N90: gscaice2g@google.com | O90: female | P90: 27462 | Q90: =DATEDIF(P90,B90,"Y") -> 49 | R90: F7C29481 | S90: 447899672801 | T90: Advanced Plus | U90: MAMMOGRAM | V90: {=IFERROR( _xlfn.XLOOKUP(1, (tblPrices[Prefix]=$AC90)*(tblPrices[Product Code]=$T90), tblPrices[Price] ), 0 ) + IF(ISNUMBER(SEARCH("Mammogram",$U90)), IFERROR(_xlfn.XLOOKUP(1,(tblPrices[Prefix]=$AC90)*(tblPrices[Product Code]="Mammogram"),tblPrices[Price]),0), 0 ) + IF(ISNUMBER(SEARCH("PSA",$U90)), IFERROR(_xlfn.XLOOKUP(1,(tblPrices[Prefix]=$AC90)*(tblPrices[Product Code]="PSA"),tblPrices[Price]),0), 0 )} -> 875 | W90: dispatched | X90: rescheduled,viewed_online,paid,fasting,red,online,ecg_uploaded | Z90: 22025312 | AA90: AXAMEMBER | AB90: {=_xlfn.LET(_xlpm.pc, UPPER(TRIM(M90)), LEFT(_xlpm.pc, MIN(FIND({0,1,2,3,4,5,6,7,8,9}, _xlpm.pc&"0123456789"))-1))} -> RG | AC90: =LEFT(AA90, 3) -> AXA | AD90: =VLOOKUP(AB90, postcode_table!A:B, 2, FALSE) -> Reading | AE90: =IFERROR(_xlfn.XLOOKUP(AC90, price_lookup_table!$C:$C, price_lookup_table!$B:$B), "") -> Self Pay
A91: ALV | B91: 45698 | C91: 45685 | D91: screening | E91: Booked | F91: Miner | G91: Radloff | H91: 76 Nobel Pass | I91: Suite 5 | M91: RG25 2PA | N91: mradloff2h@wsj.com | O91: male | P91: 27651 | Q91: =DATEDIF(P91,B91,"Y") -> 49 | R91: 46D40403 | S91: 447831647175 | T91: Advanced Plus | V91: {=IFERROR( _xlfn.XLOOKUP(1, (tblPrices[Prefix]=$AC91)*(tblPrices[Product Code]=$T91), tblPrices[Price] ), 0 ) + IF(ISNUMBER(SEARCH("Mammogram",$U91)), IFERROR(_xlfn.XLOOKUP(1,(tblPrices[Prefix]=$AC91)*(tblPrices[Product Code]="Mammogram"),tblPrices[Price]),0), 0 ) + IF(ISNUMBER(SEARCH("PSA",$U91)), IFERROR(_xlfn.XLOOKUP(1,(tblPrices[Prefix]=$AC91)*(tblPrices[Product Code]="PSA"),tblPrices[Price]),0), 0 )} -> 728 | W91: dispatched | X91: rescheduled,paid,fasting,red,online,ecg_uploaded,viewed_online | Z91: 10916346 | AA91: AXAMEMBEROFFER | AB91: {=_xlfn.LET(_xlpm.pc, UPPER(TRIM(M91)), LEFT(_xlpm.pc, MIN(FIND({0,1,2,3,4,5,6,7,8,9}, _xlpm.pc&"0123456789"))-1))} -> RG | AC91: =LEFT(AA91, 3) -> AXA | AD91: =VLOOKUP(AB91, postcode_table!A:B, 2, FALSE) -> Reading | AE91: =IFERROR(_xlfn.XLOOKUP(AC91, price_lookup_table!$C:$C, price_lookup_table!$B:$B), "") -> Self Pay
A92: CHI | B92: 45698 | C92: 45670 | D92: screening | E92: Booked | F92: Ludvig | G92: Slane | H92: 3 Mayer Way | I92: Apt 380 | M92: SL6 3PZ | N92: lslane2i@surveymonkey.com | O92: male | P92: 16723 | Q92: =DATEDIF(P92,B92,"Y") -> 79 | R92: 6F8B1F3F | S92: 447411076320 | T92: Advanced | V92: {=IFERROR( _xlfn.XLOOKUP(1, (tblPrices[Prefix]=$AC92)*(tblPrices[Product Code]=$T92), tblPrices[Price] ), 0 ) + IF(ISNUMBER(SEARCH("Mammogram",$U92)), IFERROR(_xlfn.XLOOKUP(1,(tblPrices[Prefix]=$AC92)*(tblPrices[Product Code]="Mammogram"),tblPrices[Price]),0), 0 ) + IF(ISNUMBER(SEARCH("PSA",$U92)), IFERROR(_xlfn.XLOOKUP(1,(tblPrices[Prefix]=$AC92)*(tblPrices[Product Code]="PSA"),tblPrices[Price]),0), 0 )} -> 543 | W92: dispatched | X92: rescheduled,paid,fasting,online,ecg_uploaded,viewed_online | Z92: 17533074 | AA92: AXAMEMBER | AB92: {=_xlfn.LET(_xlpm.pc, UPPER(TRIM(M92)), LEFT(_xlpm.pc, MIN(FIND({0,1,2,3,4,5,6,7,8,9}, _xlpm.pc&"0123456789"))-1))} -> SL | AC92: =LEFT(AA92, 3) -> AXA | AD92: =VLOOKUP(AB92, postcode_table!A:B, 2, FALSE) -> Slough | AE92: =IFERROR(_xlfn.XLOOKUP(AC92, price_lookup_table!$C:$C, price_lookup_table!$B:$B), "") -> Self Pay
A93: ALV | B93: 45698 | C93: 45684 | D93: screening | E93: Booked | F93: Roger | G93: Curle | H93: 522 Homewood Terrace | I93: Apt 489 | M93: SP11 0JF | N93: rcurle2j@about.me | O93: male | P93: 17616 | Q93: =DATEDIF(P93,B93,"Y") -> 76 | R93: 0FEFCE00 | S93: 447584015970 | T93: Advanced Plus | V93: {=IFERROR( _xlfn.XLOOKUP(1, (tblPrices[Prefix]=$AC93)*(tblPrices[Product Code]=$T93), tblPrices[Price] ), 0 ) + IF(ISNUMBER(SEARCH("Mammogram",$U93)), IFERROR(_xlfn.XLOOKUP(1,(tblPrices[Prefix]=$AC93)*(tblPrices[Product Code]="Mammogram"),tblPrices[Price]),0), 0 ) + IF(ISNUMBER(SEARCH("PSA",$U93)), IFERROR(_xlfn.XLOOKUP(1,(tblPrices[Prefix]=$AC93)*(tblPrices[Product Code]="PSA"),tblPrices[Price]),0), 0 )} -> 728 | W93: dispatched | X93: paid,phone_call_required,fasting,red,online,ecg_uploaded,viewed_online | Z93: 20887842 | AA93: AXAMEMBEROFFERQSLCMX2HSA | AB93: {=_xlfn.LET(_xlpm.pc, UPPER(TRIM(M93)), LEFT(_xlpm.pc, MIN(FIND({0,1,2,3,4,5,6,7,8,9}, _xlpm.pc&"0123456789"))-1))} -> SP | AC93: =LEFT(AA93, 3) -> AXA | AD93: =VLOOKUP(AB93, postcode_table!A:B, 2, FALSE) -> Salisbury | AE93: =IFERROR(_xlfn.XLOOKUP(AC93, price_lookup_table!$C:$C, price_lookup_table!$B:$B), "") -> Self Pay
A94: LIH | B94: 45698 | C94: 45665 | D94: screening | E94: Booked | F94: Vanna | G94: Meecher | H94: 38176 Hazelcrest Lane | I94: Apt 306 | M94: W2 3AA | N94: vmeecher2k@mysql.com | O94: male | P94: 17303 | Q94: =DATEDIF(P94,B94,"Y") -> 77 | R94: 5553DB50 | S94: 447730466101 | T94: Advanced | V94: {=IFERROR( _xlfn.XLOOKUP(1, (tblPrices[Prefix]=$AC94)*(tblPrices[Product Code]=$T94), tblPrices[Price] ), 0 ) + IF(ISNUMBER(SEARCH("Mammogram",$U94)), IFERROR(_xlfn.XLOOKUP(1,(tblPrices[Prefix]=$AC94)*(tblPrices[Product Code]="Mammogram"),tblPrices[Price]),0), 0 ) + IF(ISNUMBER(SEARCH("PSA",$U94)), IFERROR(_xlfn.XLOOKUP(1,(tblPrices[Prefix]=$AC94)*(tblPrices[Product Code]="PSA"),tblPrices[Price]),0), 0 )} -> 543 | W94: dispatched | X94: rescheduled,paid,fasting,online,viewed_online | Z94: 22007750 | AA94: AXAMEMBER | AB94: {=_xlfn.LET(_xlpm.pc, UPPER(TRIM(M94)), LEFT(_xlpm.pc, MIN(FIND({0,1,2,3,4,5,6,7,8,9}, _xlpm.pc&"0123456789"))-1))} -> W | AC94: =LEFT(AA94, 3) -> AXA | AD94: =VLOOKUP(AB94, postcode_table!A:B, 2, FALSE) -> West London | AE94: =IFERROR(_xlfn.XLOOKUP(AC94, price_lookup_table!$C:$C, price_lookup_table!$B:$B), "") -> Self Pay
A95: BTH | B95: 45698 | C95: 45694 | D95: screening | E95: Booked | F95: Natala | G95: Povall | H95: 06702 Bunker Hill Place | I95: Room 1311 | M95: BA1 3RS | N95: npovall2l@freewebs.com | O95: male | P95: 29918 | Q95: =DATEDIF(P95,B95,"Y") -> 43 | R95: DDFAAEE0 | S95: 447711014422 | T95: Advanced | V95: {=IFERROR( _xlfn.XLOOKUP(1, (tblPrices[Prefix]=$AC95)*(tblPrices[Product Code]=$T95), tblPrices[Price] ), 0 ) + IF(ISNUMBER(SEARCH("Mammogram",$U95)), IFERROR(_xlfn.XLOOKUP(1,(tblPrices[Prefix]=$AC95)*(tblPrices[Product Code]="Mammogram"),tblPrices[Price]),0), 0 ) + IF(ISNUMBER(SEARCH("PSA",$U95)), IFERROR(_xlfn.XLOOKUP(1,(tblPrices[Prefix]=$AC95)*(tblPrices[Product Code]="PSA"),tblPrices[Price]),0), 0 )} -> 724.5 | W95: dispatched | X95: paid,phone_call_required,fasting,online,ecg_uploaded,viewed_online | Z95: 21413353 | AA95: M01Phone | AB95: {=_xlfn.LET(_xlpm.pc, UPPER(TRIM(M95)), LEFT(_xlpm.pc, MIN(FIND({0,1,2,3,4,5,6,7,8,9}, _xlpm.pc&"0123456789"))-1))} -> BA | AC95: =LEFT(AA95, 3) -> M01 | AD95: =VLOOKUP(AB95, postcode_table!A:B, 2, FALSE) -> Bath | AE95: =IFERROR(_xlfn.XLOOKUP(AC95, price_lookup_table!$C:$C, price_lookup_table!$B:$B), "") -> Self Pay
A96: THO | B96: 45698 | C96: 45679 | D96: screening | E96: Booked | F96: Jimmie | G96: Bagshawe | H96: 66903 Dwight Circle | I96: Suite 85 | M96: S2 1WB | N96: jbagshawe2m@economist.com | O96: male | P96: 17421 | Q96: =DATEDIF(P96,B96,"Y") -> 77 | R96: A15FDCD6 | S96: 447786304471 | T96: Advanced Plus | V96: {=IFERROR( _xlfn.XLOOKUP(1, (tblPrices[Prefix]=$AC96)*(tblPrices[Product Code]=$T96), tblPrices[Price] ), 0 ) + IF(ISNUMBER(SEARCH("Mammogram",$U96)), IFERROR(_xlfn.XLOOKUP(1,(tblPrices[Prefix]=$AC96)*(tblPrices[Product Code]="Mammogram"),tblPrices[Price]),0), 0 ) + IF(ISNUMBER(SEARCH("PSA",$U96)), IFERROR(_xlfn.XLOOKUP(1,(tblPrices[Prefix]=$AC96)*(tblPrices[Product Code]="PSA"),tblPrices[Price]),0), 0 )} -> 970.5 | W96: dispatched | X96: paid,phone_call_required,fasting,red,online,viewed_online | Z96: 20735215 | AA96: M01Phone | AB96: {=_xlfn.LET(_xlpm.pc, UPPER(TRIM(M96)), LEFT(_xlpm.pc, MIN(FIND({0,1,2,3,4,5,6,7,8,9}, _xlpm.pc&"0123456789"))-1))} -> S | AC96: =LEFT(AA96, 3) -> M01 | AD96: =VLOOKUP(AB96, postcode_table!A:B, 2, FALSE) -> Sheffield | AE96: =IFERROR(_xlfn.XLOOKUP(AC96, price_lookup_table!$C:$C, price_lookup_table!$B:$B), "") -> Self Pay
A97: THO | B97: 45698 | C97: 45663 | D97: screening | E97: Booked | F97: Judd | G97: Winterton | H97: 8007 Elgar Junction | I97: 5th Floor | M97: S44 5SA | N97: jwinterton2n@stanford.edu | O97: female | P97: 23246 | Q97: =DATEDIF(P97,B97,"Y") -> 61 | R97: 880ABC6B | S97: 447970141223 | T97: Advanced Plus | V97: {=IFERROR( _xlfn.XLOOKUP(1, (tblPrices[Prefix]=$AC97)*(tblPrices[Product Code]=$T97), tblPrices[Price] ), 0 ) + IF(ISNUMBER(SEARCH("Mammogram",$U97)), IFERROR(_xlfn.XLOOKUP(1,(tblPrices[Prefix]=$AC97)*(tblPrices[Product Code]="Mammogram"),tblPrices[Price]),0), 0 ) + IF(ISNUMBER(SEARCH("PSA",$U97)), IFERROR(_xlfn.XLOOKUP(1,(tblPrices[Prefix]=$AC97)*(tblPrices[Product Code]="PSA"),tblPrices[Price]),0), 0 )} -> 970.5 | W97: dispatched | X97: paid,fasting,green,online,viewed_online | Z97: 21369823 | AA97: M01Phone | AB97: {=_xlfn.LET(_xlpm.pc, UPPER(TRIM(M97)), LEFT(_xlpm.pc, MIN(FIND({0,1,2,3,4,5,6,7,8,9}, _xlpm.pc&"0123456789"))-1))} -> S | AC97: =LEFT(AA97, 3) -> M01 | AD97: =VLOOKUP(AB97, postcode_table!A:B, 2, FALSE) -> Sheffield | AE97: =IFERROR(_xlfn.XLOOKUP(AC97, price_lookup_table!$C:$C, price_lookup_table!$B:$B), "") -> Self Pay
A98: THO | B98: 45698 | C98: 45663 | D98: screening | E98: Booked | F98: Antoine | G98: Stein | H98: 918 Dakota Place | I98: Apt 1248 | M98: S44 5SA | N98: astein2o@alexa.com | O98: male | P98: 22991 | Q98: =DATEDIF(P98,B98,"Y") -> 62 | R98: 81A206EA | S98: 447810208318 | T98: Advanced Plus | V98: {=IFERROR( _xlfn.XLOOKUP(1, (tblPrices[Prefix]=$AC98)*(tblPrices[Product Code]=$T98), tblPrices[Price] ), 0 ) + IF(ISNUMBER(SEARCH("Mammogram",$U98)), IFERROR(_xlfn.XLOOKUP(1,(tblPrices[Prefix]=$AC98)*(tblPrices[Product Code]="Mammogram"),tblPrices[Price]),0), 0 ) + IF(ISNUMBER(SEARCH("PSA",$U98)), IFERROR(_xlfn.XLOOKUP(1,(tblPrices[Prefix]=$AC98)*(tblPrices[Product Code]="PSA"),tblPrices[Price]),0), 0 )} -> 970.5 | W98: dispatched | X98: paid,fasting,green,online,viewed_online | Z98: 22005898 | AA98: M01Phone | AB98: {=_xlfn.LET(_xlpm.pc, UPPER(TRIM(M98)), LEFT(_xlpm.pc, MIN(FIND({0,1,2,3,4,5,6,7,8,9}, _xlpm.pc&"0123456789"))-1))} -> S | AC98: =LEFT(AA98, 3) -> M01 | AD98: =VLOOKUP(AB98, postcode_table!A:B, 2, FALSE) -> Sheffield | AE98: =IFERROR(_xlfn.XLOOKUP(AC98, price_lookup_table!$C:$C, price_lookup_table!$B:$B), "") -> Self Pay
A99: GAR | B99: 45699 | C99: 45670 | D99: screening | E99: Booked | F99: Andros | G99: Bartot | H99: 9 Stone Corner Lane | I99: PO Box 73984 | M99: AL1 1SN | N99: abartot2p@1und1.de | O99: female | P99: 34613 | Q99: =DATEDIF(P99,B99,"Y") -> 30 | R99: 5A15DB0D | S99: 447468595878 | T99: Advanced | V99: {=IFERROR( _xlfn.XLOOKUP(1, (tblPrices[Prefix]=$AC99)*(tblPrices[Product Code]=$T99), tblPrices[Price] ), 0 ) + IF(ISNUMBER(SEARCH("Mammogram",$U99)), IFERROR(_xlfn.XLOOKUP(1,(tblPrices[Prefix]=$AC99)*(tblPrices[Product Code]="Mammogram"),tblPrices[Price]),0), 0 ) + IF(ISNUMBER(SEARCH("PSA",$U99)), IFERROR(_xlfn.XLOOKUP(1,(tblPrices[Prefix]=$AC99)*(tblPrices[Product Code]="PSA"),tblPrices[Price]),0), 0 )} -> 543 | W99: dispatched | X99: paid,fasting,amber,online,viewed_online | Z99: 22013986 | AA99: AXAMEMBER | AB99: {=_xlfn.LET(_xlpm.pc, UPPER(TRIM(M99)), LEFT(_xlpm.pc, MIN(FIND({0,1,2,3,4,5,6,7,8,9}, _xlpm.pc&"0123456789"))-1))} -> AL | AC99: =LEFT(AA99, 3) -> AXA | AD99: =VLOOKUP(AB99, postcode_table!A:B, 2, FALSE) -> St Albans | AE99: =IFERROR(_xlfn.XLOOKUP(AC99, price_lookup_table!$C:$C, price_lookup_table!$B:$B), "") -> Self Pay
A100: GAR | B100: 45699 | C100: 45670 | D100: screening | E100: Booked | F100: Wilmer | G100: Growden | H100: 9 Kenwood Park | I100: Apt 97 | M100: AL1 1SN | N100: wgrowden2q@tripadvisor.com | O100: male | P100: 16733 | Q100: =DATEDIF(P100,B100,"Y") -> 79 | R100: D2DD5931 | S100: 447788311236 | T100: Advanced | V100: {=IFERROR( _xlfn.XLOOKUP(1, (tblPrices[Prefix]=$AC100)*(tblPrices[Product Code]=$T100), tblPrices[Price] ), 0 ) + IF(ISNUMBER(SEARCH("Mammogram",$U100)), IFERROR(_xlfn.XLOOKUP(1,(tblPrices[Prefix]=$AC100)*(tblPrices[Product Code]="Mammogram"),tblPrices[Price]),0), 0 ) + IF(ISNUMBER(SEARCH("PSA",$U100)), IFERROR(_xlfn.XLOOKUP(1,(tblPrices[Prefix]=$AC100)*(tblPrices[Product Code]="PSA"),tblPrices[Price]),0), 0 )} -> 543 | W100: dispatched | X100: paid,phone_call_required,fasting,amber | Z100: 22013972 | AA100: AXAMEMBER | AB100: {=_xlfn.LET(_xlpm.pc, UPPER(TRIM(M100)), LEFT(_xlpm.pc, MIN(FIND({0,1,2,3,4,5,6,7,8,9}, _xlpm.pc&"0123456789"))-1))} -> AL | AC100: =LEFT(AA100, 3) -> AXA | AD100: =VLOOKUP(AB100, postcode_table!A:B, 2, FALSE) -> St Albans | AE100: =IFERROR(_xlfn.XLOOKUP(AC100, price_lookup_table!$C:$C, price_lookup_table!$B:$B), "") -> Self Pay
A101: HAM | B101: 45699 | C101: 45693 | D101: screening | E101: Booked | F101: Gaspar | G101: Fennelow | H101: 9 Annamark Parkway | I101: PO Box 534 | M101: RG2 7PW | N101: gfennelow2r@vistaprint.com | O101: male | P101: 34826 | Q101: =DATEDIF(P101,B101,"Y") -> 29 | R101: 15B2FEEB | S101: 447790431123 | T101: Select | V101: {=IFERROR( _xlfn.XLOOKUP(1, (tblPrices[Prefix]=$AC101)*(tblPrices[Product Code]=$T101), tblPrices[Price] ), 0 ) + IF(ISNUMBER(SEARCH("Mammogram",$U101)), IFERROR(_xlfn.XLOOKUP(1,(tblPrices[Prefix]=$AC101)*(tblPrices[Product Code]="Mammogram"),tblPrices[Price]),0), 0 ) + IF(ISNUMBER(SEARCH("PSA",$U101)), IFERROR(_xlfn.XLOOKUP(1,(tblPrices[Prefix]=$AC101)*(tblPrices[Product Code]="PSA"),tblPrices[Price]),0), 0 )} -> 357 | W101: dispatched | X101: paid,fasting,amber,online,ecg_uploaded,viewed_online | Z101: 22044587 | AA101: AXAMEMBEROFFER4NJJLXDP59 | AB101: {=_xlfn.LET(_xlpm.pc, UPPER(TRIM(M101)), LEFT(_xlpm.pc, MIN(FIND({0,1,2,3,4,5,6,7,8,9}, _xlpm.pc&"0123456789"))-1))} -> RG | AC101: =LEFT(AA101, 3) -> AXA | AD101: =VLOOKUP(AB101, postcode_table!A:B, 2, FALSE) -> Reading | AE101: =IFERROR(_xlfn.XLOOKUP(AC101, price_lookup_table!$C:$C, price_lookup_table!$B:$B), "") -> Self Pay
...

Sheet price_lookup_table
A2: Client Name | B2: Client Type | C2: Prefix | D2: Product Code | E2: Price | F2: Price Agreement Effective From,
A3: 3D Leisure | B3: Self Pay | C3: R98 | D3: Essential | E3: 184.5 | F3: 45658
A4: 3D Leisure | B4: Self Pay | C4: R98 | D4: Select | E4: 357.38 | F4: 45658
A5: 3D Leisure | B5: Self Pay | C5: R98 | D5: Advanced | E5: 543.38 | F5: 45658
A6: 3D Leisure | B6: Self Pay | C6: R98 | D6: Advanced Plus | E6: 727.88 | F6: 45658
A7: 3D Leisure | B7: Self Pay | C7: R98 | D7: Mammogram | E7: 147 | F7: 45658
A8: 3D Leisure | B8: Self Pay | C8: R98 | D8: PSA | E8: 112 | F8: 45658
A9: A.I.A.C.E. | B9: Self Pay | C9: AIA | D9: Advanced | E9: 493 | F9: 45657
A10: A.I.A.C.E. | B10: Self Pay | C10: AIA | D10: Advanced Plus | E10: 660 | F10: 45657
A11: A.I.A.C.E. | B11: Self Pay | C11: AIA | D11: Mammogram | E11: 128 | F11: 45657
A12: A.I.A.C.E. | B12: Self Pay | C12: AIA | D12: PSA | E12: 98 | F12: 45657
A13: Airpark Service Ltd – Birmingham | B13: Corporate | C13: M06 | D13: Select | E13: 324 | F13: 45139
A14: Airpark Service Ltd – Birmingham | B14: Corporate | C14: M06 | D14: Mammogram | E14: 128 | F14: 45139
... A193: F. R. Monkhouse Ltd | B193: Corporate | C193: UJ4 | D193: Mammogram | E193: 102 | F193: 44197
A194: Fedcap | B194: Corporate | C194: UL3 | D194: Select | E194: 357 | F194: REN
A195: Fedcap | B195: Corporate | C195: UL3 | D195: Advanced | E195: 543 | F195: REN
A196: Fedcap | B196: Corporate | C196: UL3 | D196: Advanced Plus | E196: 728 | F196: REN
A197: Fedcap | B197: Corporate | C197: UL3 | D197: Mammogram | E197: 147 | F197: REN
A198: Fedcap | B198: Corporate | C198: UL3 | D198: PSA | E198: 112 | F198: REN
A199: First Rate Exchange Services Ltd | B199: Corporate | C199: U37 | D199: Advanced | E199: 586.5 | F199: 45444
A200: First Rate Exchange Services Ltd | B200: Corporate | C200: U37 | D200: Advanced Plus | E200: 786 | F200: 45444
A201: First Rate Exchange Services Ltd | B201: Corporate | C201: U37 | D201: Mammogram | E201: 140 | F201: 45444
A202: Fluor Ltd F | B202: Corporate | C202: MD7 | D202: Advanced | E202: 493 | F202: 45292
A203: Fluor Ltd F | B203: Corporate | C203: MD7 | D203: Advanced Plus | E203: 660 | F203: 45292
A204: Fluor Ltd F | B204: Corporate | C204: MD7 | D204: Mammogram | E204: 128 | F204: 45292
A205: Forester Holdings | B205: Corporate | C205: U01 | D205: Advanced | E205: 430 | F205: 43007
A206: Forester Holdings | B206: Corporate | C206: U01 | D206: Advanced Plus | E206: 575 | F206: 43007
A207: Forester Holdings | B207: Corporate | C207: U01 | D207: Mammogram | E207: 98 | F207: 43007
A208: Fresca Group Ltd | B208: Corporate | C208: MT7 | D208: Advanced | E208: 517.5 | F208: 45566
A209: Fresca Group Ltd | B209: Corporate | C209: MT7 | D209: Advanced Plus | E209: 693 | F209: 45566
A210: Fresca Group Ltd | B210: Corporate | C210: MT7 | D210: Mammogram | E210: 140 | F210: 45566
... A390: MAN Truck & Bus UK Ltd | B390: Corporate | C390: TU6 | D390: Mammogram | E390: 140 | F390: 45658
A391: Marchmont Investment | B391: Corporate | C391: SF2 | D391: Advanced | F391: 45901
A392: Marchmont Investment | B392: Corporate | C392: SF2 | D392: Advanced Plus | F392: 45901
A393: Medical Expense Consulting | B393: Corporate | C393: UA7 | D393: Essential | E393: 167.63 | F393: 45627
A394: Medical Expense Consulting | B394: Corporate | C394: UA7 | D394: Select | E394: 324.38 | F394: 45627
A395: Medical Expense Consulting | B395: Corporate | C395: UA7 | D395: Advanced | E395: 492.75 | F395: 45627
A396: Medical Expense Consulting | B396: Corporate | C396: UA7 | D396: Advanced Plus | E396: 660.38 | F396: 45627
A397: Medical Expense Consulting | B397: Corporate | C397: UA7 | D397: Mammogram | E397: 128 | F397: 45627
A398: Medical Expense Consulting | B398: Corporate | C398: UA7 | D398: PSA | E398: 98 | F398: 45627
A399: Medigold Health Consultancy Ltd | B399: Corporate | C399: UB4 | D399: Essential | E399: 132 | F399: 42370
A400: Medigold Health Consultancy Ltd | B400: Corporate | C400: UB4 | D400: Select | E400: 257 | F400: 42370
A401: Medigold Health Consultancy Ltd | B401: Corporate | C401: UB4 | D401: Advanced | E401: 370 | F401: 42370
A402: Medigold Health Consultancy Ltd | B402: Corporate | C402: UB4 | D402: Advanced Plus | E402: 500 | F402: 42370
A403: Medigold Health Consultancy Ltd | B403: Corporate | C403: UB4 | D403: PSA | E403: 65 | F403: 42370
A404: Menwith Hill Firefighters | B404: Corporate | C404: UL2 | D404: Select | E404: 454 | F404: TBC
A405: Menwith Hill Firefighters | B405: Corporate | C405: UL2 | D405: Mammogram | E405: 147 | F405: TBC
A406: Menwith Hill Firefighters | B406: Corporate | C406: UL2 | D406: PSA | E406: 112 | F406: TBC
A407: Mercury Financial Management Ltd | B407: Corporate | C407: UH5 | D407: Select | E407: 275 | F407: 43629
A408: Mercury Financial Management Ltd | B408: Corporate | C408: UH5 | D408: Advanced | E408: 417 | F408: 43629
A409: Mercury Financial Management Ltd | B409: Corporate | C409: UH5 | D409: Mammogram | E409: 102 | F409: 43629
A410: Mercury Financial Management Ltd | B410: Corporate | C410: UH5 | D410: PSA | E410: 77 | F410: 43629
A411: Merlin Attractions Operations Ltd | B411: Corporate | C411: UG6 | D411: Advanced | E411: 586.5 | F411: 45505
A412: Merlin Attractions Operations Ltd | B412: Corporate | C412: UG6 | D412: Advanced Plus | E412: 786 | F412: 45505
A413: Merlin Attractions Operations Ltd | B413: Corporate | C413: UG6 | D413: Mammogram | E413: 140 | F413: 45505
A414: Mitie Limited | B414: Corporate | C414: U76 | D414: Advanced | E414: 517.5 | F414: 45444
A415: Mitie Limited | B415: Corporate | C415: U76 | D415: Advanced Plus | E415: 693.38 | F415: 45444
A416: Mitie Limited | B416: Corporate | C416: U76 | D416: Mammogram | E416: 140 | F416: 45444
A417: Multivac UK Ltd | B417: Corporate | C417: TY4 | D417: Advanced | E417: 472.6 | F417: 44562
A418: Multivac UK Ltd | B418: Corporate | C418: TY4 | D418: Mammogram | E418: 109 | F418: 44562
... A674: Zurich Employment Services Limited | B674: Corporate Flex | C674: T35 | D674: PSA | E674: 107 | F674: 45658

Sheet postcode_table
A1: Column1 | B1: Column2
A2: Postcode area | B2: Postcode area name
A3: AB | B3: Aberdeen
A4: AL | B4: St Albans
A5: B | B5: Birmingham
A6: BA | B6: Bath
A7: BB | B7: Blackburn
A8: BD | B8: Bradford
A9: BH | B9: Bournemouth
A10: BL | B10: Bolton
A11: BN | B11: Brighton
A12: BR | B12: Bromley
... A123: ZE | B123: Lerwick
